[
  {
    "品目コード":"30000",
    "品目名":"野菜総計",
    "日付":"2026-02-27",
    "価格":280.0,
    "平均":244.7,
    "最大値":458.0,
    "最小値":142.0,
    "中央値":241.0,
    "標準偏差":35.5,
    "分散":1262.9,
    "近似曲線_値":268.493,
    "移動平均_7日":283.4,
    "移動平均_14日":279.8,
    "移動平均_30日":274.6,
    "平均(同日)":245.6,
    "中央値(同日)":237.0,
    "比率-(移動平均7日\/近似曲線_値)":5.6,
    "比率-(移動平均7日\/中央値)":17.6,
    "前年同日比(移動平均7日)":-14.1,
    "前年同日比(移動平均14日)":-13.5,
    "前年同日比(移動平均30日)":-12.3
  },
  {
    "品目コード":"30100",
    "品目名":"だいこん",
    "日付":"2026-02-27",
    "価格":79.0,
    "平均":98.3,
    "最大値":363.0,
    "最小値":44.0,
    "中央値":93.0,
    "標準偏差":29.0,
    "分散":843.3,
    "近似曲線_値":106.554,
    "移動平均_7日":83.7,
    "移動平均_14日":89.9,
    "移動平均_30日":87.3,
    "平均(同日)":95.8,
    "中央値(同日)":81.0,
    "比率-(移動平均7日\/近似曲線_値)":-21.4,
    "比率-(移動平均7日\/中央値)":-10.0,
    "前年同日比(移動平均7日)":-41.4,
    "前年同日比(移動平均14日)":-31.6,
    "前年同日比(移動平均30日)":-28.0
  },
  {
    "品目コード":"30200",
    "品目名":"かぶ",
    "日付":"2026-02-27",
    "価格":147.0,
    "平均":161.1,
    "最大値":984.0,
    "最小値":66.0,
    "中央値":151.0,
    "標準偏差":51.8,
    "分散":2681.3,
    "近似曲線_値":164.565,
    "移動平均_7日":179.0,
    "移動平均_14日":168.5,
    "移動平均_30日":158.8,
    "平均(同日)":147.5,
    "中央値(同日)":147.0,
    "比率-(移動平均7日\/近似曲線_値)":8.8,
    "比率-(移動平均7日\/中央値)":18.5,
    "前年同日比(移動平均7日)":-7.4,
    "前年同日比(移動平均14日)":-8.8,
    "前年同日比(移動平均30日)":-15.4
  },
  {
    "品目コード":"30300",
    "品目名":"にんじん",
    "日付":"2026-02-27",
    "価格":154.0,
    "平均":149.4,
    "最大値":336.0,
    "最小値":48.0,
    "中央値":138.0,
    "標準偏差":47.6,
    "分散":2264.7,
    "近似曲線_値":170.104,
    "移動平均_7日":167.9,
    "移動平均_14日":162.1,
    "移動平均_30日":151.9,
    "平均(同日)":143.2,
    "中央値(同日)":137.0,
    "比率-(移動平均7日\/近似曲線_値)":-1.3,
    "比率-(移動平均7日\/中央値)":21.7,
    "前年同日比(移動平均7日)":-24.0,
    "前年同日比(移動平均14日)":-24.0,
    "前年同日比(移動平均30日)":-24.1
  },
  {
    "品目コード":"30400",
    "品目名":"ごぼう",
    "日付":"2026-02-27",
    "価格":318.0,
    "平均":325.3,
    "最大値":679.0,
    "最小値":111.0,
    "中央値":316.0,
    "標準偏差":85.4,
    "分散":7299.2,
    "近似曲線_値":377.797,
    "移動平均_7日":330.9,
    "移動平均_14日":329.5,
    "移動平均_30日":333.9,
    "平均(同日)":351.0,
    "中央値(同日)":337.0,
    "比率-(移動平均7日\/近似曲線_値)":-12.4,
    "比率-(移動平均7日\/中央値)":4.7,
    "前年同日比(移動平均7日)":-30.9,
    "前年同日比(移動平均14日)":-31.1,
    "前年同日比(移動平均30日)":-26.1
  },
  {
    "品目コード":"30500",
    "品目名":"たけのこ",
    "日付":"2026-02-27",
    "価格":1870.0,
    "平均":1037.4,
    "最大値":8694.0,
    "最小値":4.0,
    "中央値":844.0,
    "標準偏差":765.7,
    "分散":586242.1,
    "近似曲線_値":1445.259,
    "移動平均_7日":2162.3,
    "移動平均_14日":2232.6,
    "移動平均_30日":2117.8,
    "平均(同日)":1656.1,
    "中央値(同日)":1454.0,
    "比率-(移動平均7日\/近似曲線_値)":49.6,
    "比率-(移動平均7日\/中央値)":156.2,
    "前年同日比(移動平均7日)":-23.0,
    "前年同日比(移動平均14日)":-17.4,
    "前年同日比(移動平均30日)":-14.6
  },
  {
    "品目コード":"30600",
    "品目名":"れんこん",
    "日付":"2026-02-27",
    "価格":414.0,
    "平均":572.2,
    "最大値":1778.0,
    "最小値":27.0,
    "中央値":489.0,
    "標準偏差":245.7,
    "分散":60387.8,
    "近似曲線_値":490.017,
    "移動平均_7日":394.4,
    "移動平均_14日":391.4,
    "移動平均_30日":376.2,
    "平均(同日)":496.1,
    "中央値(同日)":482.0,
    "比率-(移動平均7日\/近似曲線_値)":-19.5,
    "比率-(移動平均7日\/中央値)":-19.3,
    "前年同日比(移動平均7日)":-14.3,
    "前年同日比(移動平均14日)":-12.3,
    "前年同日比(移動平均30日)":-12.9
  },
  {
    "品目コード":"31100",
    "品目名":"はくさい",
    "日付":"2026-02-27",
    "価格":57.0,
    "平均":84.0,
    "最大値":342.0,
    "最小値":25.0,
    "中央値":76.0,
    "標準偏差":35.3,
    "分散":1247.4,
    "近似曲線_値":83.993,
    "移動平均_7日":57.3,
    "移動平均_14日":61.4,
    "移動平均_30日":61.6,
    "平均(同日)":84.0,
    "中央値(同日)":72.0,
    "比率-(移動平均7日\/近似曲線_値)":-31.8,
    "比率-(移動平均7日\/中央値)":-24.6,
    "前年同日比(移動平均7日)":-68.1,
    "前年同日比(移動平均14日)":-64.4,
    "前年同日比(移動平均30日)":-60.4
  },
  {
    "品目コード":"31300",
    "品目名":"みずな",
    "日付":"2026-02-27",
    "価格":323.0,
    "平均":404.3,
    "最大値":1576.0,
    "最小値":187.0,
    "中央値":373.0,
    "標準偏差":149.8,
    "分散":22453.2,
    "近似曲線_値":398.802,
    "移動平均_7日":355.1,
    "移動平均_14日":379.8,
    "移動平均_30日":400.5,
    "平均(同日)":311.5,
    "中央値(同日)":298.0,
    "比率-(移動平均7日\/近似曲線_値)":-11.0,
    "比率-(移動平均7日\/中央値)":-4.8,
    "前年同日比(移動平均7日)":-30.3,
    "前年同日比(移動平均14日)":-20.6,
    "前年同日比(移動平均30日)":-11.8
  },
  {
    "品目コード":"31500",
    "品目名":"こまつな",
    "日付":"2026-02-27",
    "価格":287.0,
    "平均":334.2,
    "最大値":922.0,
    "最小値":84.0,
    "中央値":315.0,
    "標準偏差":118.3,
    "分散":13986.1,
    "近似曲線_値":335.144,
    "移動平均_7日":346.7,
    "移動平均_14日":390.1,
    "移動平均_30日":415.2,
    "平均(同日)":312.2,
    "中央値(同日)":315.0,
    "比率-(移動平均7日\/近似曲線_値)":3.4,
    "比率-(移動平均7日\/中央値)":10.1,
    "前年同日比(移動平均7日)":-27.9,
    "前年同日比(移動平均14日)":-18.6,
    "前年同日比(移動平均30日)":-10.5
  },
  {
    "品目コード":"31550",
    "品目名":"その他の菜類",
    "日付":"2026-02-27",
    "価格":428.0,
    "平均":426.3,
    "最大値":1377.0,
    "最小値":142.0,
    "中央値":405.0,
    "標準偏差":112.3,
    "分散":12619.7,
    "近似曲線_値":478.475,
    "移動平均_7日":420.6,
    "移動平均_14日":432.1,
    "移動平均_30日":437.8,
    "平均(同日)":378.5,
    "中央値(同日)":359.0,
    "比率-(移動平均7日\/近似曲線_値)":-12.1,
    "比率-(移動平均7日\/中央値)":3.9,
    "前年同日比(移動平均7日)":-16.0,
    "前年同日比(移動平均14日)":-14.9,
    "前年同日比(移動平均30日)":-10.4
  },
  {
    "品目コード":"31560",
    "品目名":"ちんげんさい",
    "日付":"2026-02-27",
    "価格":334.0,
    "平均":335.6,
    "最大値":878.0,
    "最小値":118.0,
    "中央値":322.0,
    "標準偏差":87.6,
    "分散":7676.4,
    "近似曲線_値":366.138,
    "移動平均_7日":363.7,
    "移動平均_14日":372.6,
    "移動平均_30日":373.9,
    "平均(同日)":320.7,
    "中央値(同日)":327.0,
    "比率-(移動平均7日\/近似曲線_値)":-0.7,
    "比率-(移動平均7日\/中央値)":13.0,
    "前年同日比(移動平均7日)":-11.6,
    "前年同日比(移動平均14日)":-11.2,
    "前年同日比(移動平均30日)":-13.6
  },
  {
    "品目コード":"31700",
    "品目名":"キャベツ",
    "日付":"2026-02-27",
    "価格":97.0,
    "平均":100.1,
    "最大値":407.0,
    "最小値":17.0,
    "中央値":89.0,
    "標準偏差":41.3,
    "分散":1702.2,
    "近似曲線_値":107.058,
    "移動平均_7日":99.1,
    "移動平均_14日":101.7,
    "移動平均_30日":101.8,
    "平均(同日)":104.0,
    "中央値(同日)":93.0,
    "比率-(移動平均7日\/近似曲線_値)":-7.4,
    "比率-(移動平均7日\/中央値)":11.3,
    "前年同日比(移動平均7日)":-52.4,
    "前年同日比(移動平均14日)":-50.7,
    "前年同日比(移動平均30日)":-48.3
  },
  {
    "品目コード":"31800",
    "品目名":"ほうれんそう",
    "日付":"2026-02-27",
    "価格":370.0,
    "平均":621.3,
    "最大値":1944.0,
    "最小値":151.0,
    "中央値":559.0,
    "標準偏差":207.0,
    "分散":42842.1,
    "近似曲線_値":643.874,
    "移動平均_7日":426.7,
    "移動平均_14日":490.4,
    "移動平均_30日":526.0,
    "平均(同日)":428.0,
    "中央値(同日)":392.0,
    "比率-(移動平均7日\/近似曲線_値)":-33.7,
    "比率-(移動平均7日\/中央値)":-23.7,
    "前年同日比(移動平均7日)":-26.3,
    "前年同日比(移動平均14日)":-18.9,
    "前年同日比(移動平均30日)":-9.6
  },
  {
    "品目コード":"31900",
    "品目名":"ねぎ",
    "日付":"2026-02-27",
    "価格":456.0,
    "平均":437.0,
    "最大値":1143.0,
    "最小値":186.0,
    "中央値":432.0,
    "標準偏差":85.6,
    "分散":7334.5,
    "近似曲線_値":470.476,
    "移動平均_7日":465.4,
    "移動平均_14日":468.3,
    "移動平均_30日":439.2,
    "平均(同日)":430.5,
    "中央値(同日)":417.0,
    "比率-(移動平均7日\/近似曲線_値)":-1.1,
    "比率-(移動平均7日\/中央値)":7.7,
    "前年同日比(移動平均7日)":-30.4,
    "前年同日比(移動平均14日)":-26.4,
    "前年同日比(移動平均30日)":-22.0
  },
  {
    "品目コード":"32300",
    "品目名":"ふき",
    "日付":"2026-02-27",
    "価格":702.0,
    "平均":383.8,
    "最大値":1563.0,
    "最小値":24.0,
    "中央値":350.0,
    "標準偏差":223.5,
    "分散":49972.2,
    "近似曲線_値":457.429,
    "移動平均_7日":704.7,
    "移動平均_14日":650.6,
    "移動平均_30日":574.0,
    "平均(同日)":468.5,
    "中央値(同日)":426.0,
    "比率-(移動平均7日\/近似曲線_値)":54.1,
    "比率-(移動平均7日\/中央値)":101.3,
    "前年同日比(移動平均7日)":7.0,
    "前年同日比(移動平均14日)":6.9,
    "前年同日比(移動平均30日)":4.1
  },
  {
    "品目コード":"32400",
    "品目名":"うど",
    "日付":"2025-12-28",
    "価格":603.0,
    "平均":694.6,
    "最大値":3645.0,
    "最小値":189.0,
    "中央値":644.0,
    "標準偏差":246.7,
    "分散":60882.7,
    "近似曲線_値":806.318,
    "移動平均_7日":720.7,
    "移動平均_14日":731.9,
    "移動平均_30日":732.9,
    "平均(同日)":684.2,
    "中央値(同日)":655.5,
    "比率-(移動平均7日\/近似曲線_値)":-10.6,
    "比率-(移動平均7日\/中央値)":11.9,
    "前年同日比(移動平均7日)":-19.8,
    "前年同日比(移動平均14日)":-19.9,
    "前年同日比(移動平均30日)":-23.9
  },
  {
    "品目コード":"32500",
    "品目名":"みつば",
    "日付":"2026-02-27",
    "価格":629.0,
    "平均":653.6,
    "最大値":2916.0,
    "最小値":290.0,
    "中央値":563.0,
    "標準偏差":299.8,
    "分散":89882.6,
    "近似曲線_値":739.313,
    "移動平均_7日":690.1,
    "移動平均_14日":635.9,
    "移動平均_30日":647.0,
    "平均(同日)":547.8,
    "中央値(同日)":544.0,
    "比率-(移動平均7日\/近似曲線_値)":-6.7,
    "比率-(移動平均7日\/中央値)":22.6,
    "前年同日比(移動平均7日)":5.7,
    "前年同日比(移動平均14日)":3.5,
    "前年同日比(移動平均30日)":-1.5
  },
  {
    "品目コード":"32600",
    "品目名":"しゅんぎく",
    "日付":"2026-02-27",
    "価格":568.0,
    "平均":803.6,
    "最大値":2098.0,
    "最小値":58.0,
    "中央値":689.0,
    "標準偏差":357.9,
    "分散":128074.2,
    "近似曲線_値":950.87,
    "移動平均_7日":620.4,
    "移動平均_14日":691.7,
    "移動平均_30日":741.7,
    "平均(同日)":509.1,
    "中央値(同日)":508.0,
    "比率-(移動平均7日\/近似曲線_値)":-34.8,
    "比率-(移動平均7日\/中央値)":-10.0,
    "前年同日比(移動平均7日)":-16.7,
    "前年同日比(移動平均14日)":-8.8,
    "前年同日比(移動平均30日)":1.8
  },
  {
    "品目コード":"32800",
    "品目名":"にら",
    "日付":"2026-02-27",
    "価格":853.0,
    "平均":733.7,
    "最大値":2464.0,
    "最小値":175.0,
    "中央値":732.0,
    "標準偏差":242.9,
    "分散":59009.6,
    "近似曲線_値":818.862,
    "移動平均_7日":941.3,
    "移動平均_14日":949.9,
    "移動平均_30日":960.5,
    "平均(同日)":765.7,
    "中央値(同日)":773.0,
    "比率-(移動平均7日\/近似曲線_値)":15.0,
    "比率-(移動平均7日\/中央値)":28.6,
    "前年同日比(移動平均7日)":-9.7,
    "前年同日比(移動平均14日)":-7.4,
    "前年同日比(移動平均30日)":-5.5
  },
  {
    "品目コード":"32900",
    "品目名":"セルリー",
    "日付":"2026-02-27",
    "価格":253.0,
    "平均":273.1,
    "最大値":600.0,
    "最小値":66.0,
    "中央値":274.0,
    "標準偏差":59.4,
    "分散":3523.2,
    "近似曲線_値":281.073,
    "移動平均_7日":229.6,
    "移動平均_14日":228.9,
    "移動平均_30日":229.1,
    "平均(同日)":254.4,
    "中央値(同日)":246.0,
    "比率-(移動平均7日\/近似曲線_値)":-18.3,
    "比率-(移動平均7日\/中央値)":-16.2,
    "前年同日比(移動平均7日)":-14.0,
    "前年同日比(移動平均14日)":-15.9,
    "前年同日比(移動平均30日)":-14.5
  },
  {
    "品目コード":"33100",
    "品目名":"アスパラガス",
    "日付":"2026-02-27",
    "価格":1745.0,
    "平均":1288.0,
    "最大値":3562.0,
    "最小値":72.0,
    "中央値":1240.0,
    "標準偏差":357.0,
    "分散":127477.1,
    "近似曲線_値":1509.635,
    "移動平均_7日":1813.3,
    "移動平均_14日":1782.5,
    "移動平均_30日":1766.5,
    "平均(同日)":1255.0,
    "中央値(同日)":1111.0,
    "比率-(移動平均7日\/近似曲線_値)":20.1,
    "比率-(移動平均7日\/中央値)":46.2,
    "前年同日比(移動平均7日)":18.5,
    "前年同日比(移動平均14日)":19.4,
    "前年同日比(移動平均30日)":21.5
  },
  {
    "品目コード":"33200",
    "品目名":"カリフラワー",
    "日付":"2026-02-27",
    "価格":174.0,
    "平均":274.6,
    "最大値":1215.0,
    "最小値":51.0,
    "中央値":261.0,
    "標準偏差":83.1,
    "分散":6910.1,
    "近似曲線_値":265.379,
    "移動平均_7日":173.1,
    "移動平均_14日":182.4,
    "移動平均_30日":210.8,
    "平均(同日)":220.0,
    "中央値(同日)":217.0,
    "比率-(移動平均7日\/近似曲線_値)":-34.8,
    "比率-(移動平均7日\/中央値)":-33.7,
    "前年同日比(移動平均7日)":-37.5,
    "前年同日比(移動平均14日)":-39.1,
    "前年同日比(移動平均30日)":-30.9
  },
  {
    "品目コード":"33300",
    "品目名":"ブロッコリー",
    "日付":"2026-02-27",
    "価格":286.0,
    "平均":438.2,
    "最大値":949.0,
    "最小値":106.0,
    "中央値":433.0,
    "標準偏差":111.7,
    "分散":12475.7,
    "近似曲線_値":452.774,
    "移動平均_7日":290.7,
    "移動平均_14日":321.6,
    "移動平均_30日":378.7,
    "平均(同日)":357.1,
    "中央値(同日)":319.0,
    "比率-(移動平均7日\/近似曲線_値)":-35.8,
    "比率-(移動平均7日\/中央値)":-32.9,
    "前年同日比(移動平均7日)":-48.7,
    "前年同日比(移動平均14日)":-46.5,
    "前年同日比(移動平均30日)":-36.2
  },
  {
    "品目コード":"33400",
    "品目名":"レタス",
    "日付":"2026-02-27",
    "価格":197.0,
    "平均":202.3,
    "最大値":726.0,
    "最小値":36.0,
    "中央値":184.0,
    "標準偏差":82.4,
    "分散":6788.8,
    "近似曲線_値":200.152,
    "移動平均_7日":196.3,
    "移動平均_14日":219.0,
    "移動平均_30日":231.0,
    "平均(同日)":211.4,
    "中央値(同日)":197.0,
    "比率-(移動平均7日\/近似曲線_値)":-1.9,
    "比率-(移動平均7日\/中央値)":6.7,
    "前年同日比(移動平均7日)":-27.7,
    "前年同日比(移動平均14日)":-23.3,
    "前年同日比(移動平均30日)":-20.9
  },
  {
    "品目コード":"33600",
    "品目名":"パセリ",
    "日付":"2025-12-28",
    "価格":1973.0,
    "平均":1539.1,
    "最大値":11751.0,
    "最小値":54.0,
    "中央値":1229.0,
    "標準偏差":945.8,
    "分散":894621.0,
    "近似曲線_値":1976.706,
    "移動平均_7日":2049.7,
    "移動平均_14日":2035.2,
    "移動平均_30日":1845.5,
    "平均(同日)":2333.0,
    "中央値(同日)":2074.5,
    "比率-(移動平均7日\/近似曲線_値)":3.7,
    "比率-(移動平均7日\/中央値)":66.8,
    "前年同日比(移動平均7日)":-51.1,
    "前年同日比(移動平均14日)":-44.4,
    "前年同日比(移動平均30日)":-40.5
  },
  {
    "品目コード":"34100",
    "品目名":"きゅうり",
    "日付":"2026-02-27",
    "価格":378.0,
    "平均":358.9,
    "最大値":1040.0,
    "最小値":132.0,
    "中央値":340.0,
    "標準偏差":117.4,
    "分散":13782.6,
    "近似曲線_値":398.835,
    "移動平均_7日":367.9,
    "移動平均_14日":389.1,
    "移動平均_30日":417.6,
    "平均(同日)":369.9,
    "中央値(同日)":378.0,
    "比率-(移動平均7日\/近似曲線_値)":-7.8,
    "比率-(移動平均7日\/中央値)":8.2,
    "前年同日比(移動平均7日)":-8.7,
    "前年同日比(移動平均14日)":-9.5,
    "前年同日比(移動平均30日)":-11.3
  },
  {
    "品目コード":"34200",
    "品目名":"かぼちゃ",
    "日付":"2026-02-27",
    "価格":212.0,
    "平均":222.9,
    "最大値":1100.0,
    "最小値":95.0,
    "中央値":206.0,
    "標準偏差":84.5,
    "分散":7148.5,
    "近似曲線_値":278.023,
    "移動平均_7日":254.4,
    "移動平均_14日":242.9,
    "移動平均_30日":240.0,
    "平均(同日)":225.1,
    "中央値(同日)":170.0,
    "比率-(移動平均7日\/近似曲線_値)":-8.5,
    "比率-(移動平均7日\/中央値)":23.5,
    "前年同日比(移動平均7日)":-21.8,
    "前年同日比(移動平均14日)":-19.6,
    "前年同日比(移動平均30日)":-21.5
  },
  {
    "品目コード":"34300",
    "品目名":"なす",
    "日付":"2026-02-27",
    "価格":460.0,
    "平均":402.2,
    "最大値":926.0,
    "最小値":95.0,
    "中央値":399.0,
    "標準偏差":79.2,
    "分散":6274.1,
    "近似曲線_値":410.908,
    "移動平均_7日":439.7,
    "移動平均_14日":446.6,
    "移動平均_30日":439.5,
    "平均(同日)":446.5,
    "中央値(同日)":448.0,
    "比率-(移動平均7日\/近似曲線_値)":7.0,
    "比率-(移動平均7日\/中央値)":10.2,
    "前年同日比(移動平均7日)":3.6,
    "前年同日比(移動平均14日)":1.1,
    "前年同日比(移動平均30日)":-7.0
  },
  {
    "品目コード":"34400",
    "品目名":"トマト",
    "日付":"2026-02-27",
    "価格":418.0,
    "平均":406.3,
    "最大値":1147.0,
    "最小値":146.0,
    "中央値":377.0,
    "標準偏差":128.3,
    "分散":16460.9,
    "近似曲線_値":467.206,
    "移動平均_7日":386.0,
    "移動平均_14日":393.5,
    "移動平均_30日":390.7,
    "平均(同日)":385.3,
    "中央値(同日)":391.0,
    "比率-(移動平均7日\/近似曲線_値)":-17.4,
    "比率-(移動平均7日\/中央値)":2.4,
    "前年同日比(移動平均7日)":-5.3,
    "前年同日比(移動平均14日)":-4.9,
    "前年同日比(移動平均30日)":-4.0
  },
  {
    "品目コード":"34450",
    "品目名":"ミニトマト",
    "日付":"2026-02-27",
    "価格":637.0,
    "平均":698.5,
    "最大値":1760.0,
    "最小値":326.0,
    "中央値":664.0,
    "標準偏差":203.2,
    "分散":41270.4,
    "近似曲線_値":734.276,
    "移動平均_7日":631.0,
    "移動平均_14日":645.6,
    "移動平均_30日":634.5,
    "平均(同日)":722.5,
    "中央値(同日)":733.0,
    "比率-(移動平均7日\/近似曲線_値)":-14.1,
    "比率-(移動平均7日\/中央値)":-5.0,
    "前年同日比(移動平均7日)":-19.4,
    "前年同日比(移動平均14日)":-18.4,
    "前年同日比(移動平均30日)":-15.7
  },
  {
    "品目コード":"34500",
    "品目名":"ピーマン",
    "日付":"2026-02-27",
    "価格":722.0,
    "平均":515.1,
    "最大値":1113.0,
    "最小値":173.0,
    "中央値":493.0,
    "標準偏差":144.7,
    "分散":20937.2,
    "近似曲線_値":593.908,
    "移動平均_7日":695.1,
    "移動平均_14日":726.8,
    "移動平均_30日":735.7,
    "平均(同日)":703.2,
    "中央値(同日)":722.0,
    "比率-(移動平均7日\/近似曲線_値)":17.0,
    "比率-(移動平均7日\/中央値)":41.0,
    "前年同日比(移動平均7日)":-10.5,
    "前年同日比(移動平均14日)":-9.5,
    "前年同日比(移動平均30日)":-8.2
  },
  {
    "品目コード":"34600",
    "品目名":"ししとう",
    "日付":"2026-02-27",
    "価格":2009.0,
    "平均":1479.8,
    "最大値":5130.0,
    "最小値":324.0,
    "中央値":1353.0,
    "標準偏差":510.5,
    "分散":260649.0,
    "近似曲線_値":1774.097,
    "移動平均_7日":1895.4,
    "移動平均_14日":1933.9,
    "移動平均_30日":2013.8,
    "平均(同日)":1610.2,
    "中央値(同日)":1404.0,
    "比率-(移動平均7日\/近似曲線_値)":6.8,
    "比率-(移動平均7日\/中央値)":40.1,
    "前年同日比(移動平均7日)":0.9,
    "前年同日比(移動平均14日)":0.6,
    "前年同日比(移動平均30日)":6.9
  },
  {
    "品目コード":"34700",
    "品目名":"スイトコーン",
    "日付":"2026-02-27",
    "価格":532.0,
    "平均":356.8,
    "最大値":1813.0,
    "最小値":16.0,
    "中央値":330.0,
    "標準偏差":134.5,
    "分散":18092.8,
    "近似曲線_値":417.657,
    "移動平均_7日":594.1,
    "移動平均_14日":587.9,
    "移動平均_30日":538.1,
    "平均(同日)":438.7,
    "中央値(同日)":432.0,
    "比率-(移動平均7日\/近似曲線_値)":42.2,
    "比率-(移動平均7日\/中央値)":80.0,
    "前年同日比(移動平均7日)":-8.8,
    "前年同日比(移動平均14日)":-12.1,
    "前年同日比(移動平均30日)":-10.2
  },
  {
    "品目コード":"35100",
    "品目名":"さやいんげん",
    "日付":"2026-02-27",
    "価格":1057.0,
    "平均":1006.1,
    "最大値":2528.0,
    "最小値":180.0,
    "中央値":950.0,
    "標準偏差":263.7,
    "分散":69538.2,
    "近似曲線_値":1158.205,
    "移動平均_7日":1120.7,
    "移動平均_14日":1154.9,
    "移動平均_30日":1177.8,
    "平均(同日)":996.6,
    "中央値(同日)":1001.0,
    "比率-(移動平均7日\/近似曲線_値)":-3.2,
    "比率-(移動平均7日\/中央値)":18.0,
    "前年同日比(移動平均7日)":-22.4,
    "前年同日比(移動平均14日)":-21.2,
    "前年同日比(移動平均30日)":-19.1
  },
  {
    "品目コード":"35200",
    "品目名":"さやえんどう",
    "日付":"2026-02-27",
    "価格":1305.0,
    "平均":1559.9,
    "最大値":6638.0,
    "最小値":621.0,
    "中央値":1361.0,
    "標準偏差":624.2,
    "分散":389626.1,
    "近似曲線_値":1730.934,
    "移動平均_7日":1279.9,
    "移動平均_14日":1216.9,
    "移動平均_30日":1142.5,
    "平均(同日)":1305.3,
    "中央値(同日)":1305.0,
    "比率-(移動平均7日\/近似曲線_値)":-26.1,
    "比率-(移動平均7日\/中央値)":-6.0,
    "前年同日比(移動平均7日)":-3.2,
    "前年同日比(移動平均14日)":-8.6,
    "前年同日比(移動平均30日)":-18.4
  },
  {
    "品目コード":"35300",
    "品目名":"実えんどう",
    "日付":"2026-02-27",
    "価格":937.0,
    "平均":848.5,
    "最大値":5184.0,
    "最小値":108.0,
    "中央値":887.0,
    "標準偏差":359.6,
    "分散":129346.5,
    "近似曲線_値":889.382,
    "移動平均_7日":965.0,
    "移動平均_14日":978.0,
    "移動平均_30日":947.9,
    "平均(同日)":973.2,
    "中央値(同日)":937.0,
    "比率-(移動平均7日\/近似曲線_値)":8.5,
    "比率-(移動平均7日\/中央値)":8.8,
    "前年同日比(移動平均7日)":-14.6,
    "前年同日比(移動平均14日)":-13.5,
    "前年同日比(移動平均30日)":-15.4
  },
  {
    "品目コード":"35400",
    "品目名":"そらまめ",
    "日付":"2026-02-27",
    "価格":922.0,
    "平均":728.4,
    "最大値":2990.0,
    "最小値":1.0,
    "中央値":645.0,
    "標準偏差":357.7,
    "分散":127953.7,
    "近似曲線_値":693.406,
    "移動平均_7日":989.7,
    "移動平均_14日":1034.7,
    "移動平均_30日":975.9,
    "平均(同日)":970.7,
    "中央値(同日)":816.0,
    "比率-(移動平均7日\/近似曲線_値)":42.7,
    "比率-(移動平均7日\/中央値)":53.4,
    "前年同日比(移動平均7日)":-8.8,
    "前年同日比(移動平均14日)":-6.1,
    "前年同日比(移動平均30日)":-12.7
  },
  {
    "品目コード":"35500",
    "品目名":"えだまめ",
    "日付":"2026-02-27",
    "価格":2641.0,
    "平均":1327.2,
    "最大値":2952.0,
    "最小値":54.0,
    "中央値":1064.0,
    "標準偏差":641.3,
    "分散":411308.3,
    "近似曲線_値":1539.071,
    "移動平均_7日":2393.4,
    "移動平均_14日":2296.4,
    "移動平均_30日":2552.0,
    "平均(同日)":2365.4,
    "中央値(同日)":2408.0,
    "比率-(移動平均7日\/近似曲線_値)":55.5,
    "比率-(移動平均7日\/中央値)":124.9,
    "前年同日比(移動平均7日)":-8.7,
    "前年同日比(移動平均14日)":-11.7,
    "前年同日比(移動平均30日)":-1.7
  },
  {
    "品目コード":"36100",
    "品目名":"かんしょ",
    "日付":"2026-02-27",
    "価格":286.0,
    "平均":272.9,
    "最大値":468.0,
    "最小値":89.0,
    "中央値":273.0,
    "標準偏差":44.3,
    "分散":1958.8,
    "近似曲線_値":314.546,
    "移動平均_7日":281.3,
    "移動平均_14日":278.4,
    "移動平均_30日":274.7,
    "平均(同日)":251.1,
    "中央値(同日)":243.0,
    "比率-(移動平均7日\/近似曲線_値)":-10.6,
    "比率-(移動平均7日\/中央値)":3.0,
    "前年同日比(移動平均7日)":6.7,
    "前年同日比(移動平均14日)":4.7,
    "前年同日比(移動平均30日)":4.6
  },
  {
    "品目コード":"36200",
    "品目名":"ばれいしょ",
    "日付":"2026-02-27",
    "価格":314.0,
    "平均":168.2,
    "最大値":452.0,
    "最小値":59.0,
    "中央値":152.0,
    "標準偏差":63.5,
    "分散":4028.5,
    "近似曲線_値":198.869,
    "移動平均_7日":304.4,
    "移動平均_14日":300.1,
    "移動平均_30日":297.4,
    "平均(同日)":188.3,
    "中央値(同日)":191.0,
    "比率-(移動平均7日\/近似曲線_値)":53.1,
    "比率-(移動平均7日\/中央値)":100.3,
    "前年同日比(移動平均7日)":29.2,
    "前年同日比(移動平均14日)":30.5,
    "前年同日比(移動平均30日)":30.5
  },
  {
    "品目コード":"36300",
    "品目名":"さといも",
    "日付":"2026-02-27",
    "価格":359.0,
    "平均":366.5,
    "最大値":1111.0,
    "最小値":5.0,
    "中央値":344.0,
    "標準偏差":99.8,
    "分散":9968.4,
    "近似曲線_値":425.107,
    "移動平均_7日":362.3,
    "移動平均_14日":363.3,
    "移動平均_30日":364.7,
    "平均(同日)":319.2,
    "中央値(同日)":306.0,
    "比率-(移動平均7日\/近似曲線_値)":-14.8,
    "比率-(移動平均7日\/中央値)":5.3,
    "前年同日比(移動平均7日)":-22.7,
    "前年同日比(移動平均14日)":-17.7,
    "前年同日比(移動平均30日)":-13.4
  },
  {
    "品目コード":"36500",
    "品目名":"やまのいも",
    "日付":"2026-02-27",
    "価格":406.0,
    "平均":388.3,
    "最大値":855.0,
    "最小値":54.0,
    "中央値":377.0,
    "標準偏差":80.3,
    "分散":6453.8,
    "近似曲線_値":394.141,
    "移動平均_7日":431.4,
    "移動平均_14日":421.9,
    "移動平均_30日":419.4,
    "平均(同日)":365.4,
    "中央値(同日)":368.0,
    "比率-(移動平均7日\/近似曲線_値)":9.5,
    "比率-(移動平均7日\/中央値)":14.4,
    "前年同日比(移動平均7日)":3.1,
    "前年同日比(移動平均14日)":-1.1,
    "前年同日比(移動平均30日)":-2.7
  },
  {
    "品目コード":"36610",
    "品目名":"たまねぎ",
    "日付":"2026-02-27",
    "価格":214.0,
    "平均":122.2,
    "最大値":453.0,
    "最小値":42.0,
    "中央値":109.0,
    "標準偏差":45.2,
    "分散":2047.3,
    "近似曲線_値":162.663,
    "移動平均_7日":245.4,
    "移動平均_14日":245.3,
    "移動平均_30日":242.1,
    "平均(同日)":133.2,
    "中央値(同日)":126.0,
    "比率-(移動平均7日\/近似曲線_値)":50.9,
    "比率-(移動平均7日\/中央値)":125.1,
    "前年同日比(移動平均7日)":59.0,
    "前年同日比(移動平均14日)":59.4,
    "前年同日比(移動平均30日)":56.0
  },
  {
    "品目コード":"36700",
    "品目名":"にんにく",
    "日付":"2026-02-27",
    "価格":1091.0,
    "平均":1004.7,
    "最大値":1846.0,
    "最小値":278.0,
    "中央値":998.0,
    "標準偏差":231.0,
    "分散":53339.5,
    "近似曲線_値":1065.096,
    "移動平均_7日":1160.1,
    "移動平均_14日":1166.4,
    "移動平均_30日":1188.1,
    "平均(同日)":1080.5,
    "中央値(同日)":1049.0,
    "比率-(移動平均7日\/近似曲線_値)":8.9,
    "比率-(移動平均7日\/中央値)":16.2,
    "前年同日比(移動平均7日)":-2.7,
    "前年同日比(移動平均14日)":-5.3,
    "前年同日比(移動平均30日)":-3.6
  },
  {
    "品目コード":"37200",
    "品目名":"しょうが",
    "日付":"2026-02-27",
    "価格":1054.0,
    "平均":708.8,
    "最大値":1337.0,
    "最小値":234.0,
    "中央値":666.0,
    "標準偏差":148.3,
    "分散":22000.3,
    "近似曲線_値":780.777,
    "移動平均_7日":1095.4,
    "移動平均_14日":1077.6,
    "移動平均_30日":1075.0,
    "平均(同日)":714.0,
    "中央値(同日)":655.0,
    "比率-(移動平均7日\/近似曲線_値)":40.3,
    "比率-(移動平均7日\/中央値)":64.5,
    "前年同日比(移動平均7日)":10.1,
    "前年同日比(移動平均14日)":6.0,
    "前年同日比(移動平均30日)":6.8
  },
  {
    "品目コード":"38100",
    "品目名":"生しいたけ",
    "日付":"2026-02-27",
    "価格":1036.0,
    "平均":966.9,
    "最大値":2341.0,
    "最小値":354.0,
    "中央値":947.0,
    "標準偏差":147.7,
    "分散":21814.7,
    "近似曲線_値":1007.572,
    "移動平均_7日":1152.0,
    "移動平均_14日":1120.6,
    "移動平均_30日":1100.2,
    "平均(同日)":989.2,
    "中央値(同日)":1012.0,
    "比率-(移動平均7日\/近似曲線_値)":14.3,
    "比率-(移動平均7日\/中央値)":21.6,
    "前年同日比(移動平均7日)":3.2,
    "前年同日比(移動平均14日)":2.0,
    "前年同日比(移動平均30日)":0.7
  },
  {
    "品目コード":"38300",
    "品目名":"なめこ",
    "日付":"2026-02-27",
    "価格":487.0,
    "平均":464.8,
    "最大値":1026.0,
    "最小値":291.0,
    "中央値":458.0,
    "標準偏差":66.6,
    "分散":4441.2,
    "近似曲線_値":484.803,
    "移動平均_7日":533.6,
    "移動平均_14日":515.6,
    "移動平均_30日":511.0,
    "平均(同日)":474.7,
    "中央値(同日)":478.0,
    "比率-(移動平均7日\/近似曲線_値)":10.1,
    "比率-(移動平均7日\/中央値)":16.5,
    "前年同日比(移動平均7日)":-4.6,
    "前年同日比(移動平均14日)":-5.5,
    "前年同日比(移動平均30日)":-6.3
  },
  {
    "品目コード":"38400",
    "品目名":"えのきだけ",
    "日付":"2026-02-27",
    "価格":372.0,
    "平均":271.4,
    "最大値":742.0,
    "最小値":67.0,
    "中央値":262.0,
    "標準偏差":83.3,
    "分散":6939.8,
    "近似曲線_値":342.804,
    "移動平均_7日":395.7,
    "移動平均_14日":391.1,
    "移動平均_30日":394.5,
    "平均(同日)":269.7,
    "中央値(同日)":268.0,
    "比率-(移動平均7日\/近似曲線_値)":15.4,
    "比率-(移動平均7日\/中央値)":51.0,
    "前年同日比(移動平均7日)":8.5,
    "前年同日比(移動平均14日)":8.3,
    "前年同日比(移動平均30日)":5.6
  },
  {
    "品目コード":"38500",
    "品目名":"しめじ",
    "日付":"2026-02-27",
    "価格":503.0,
    "平均":449.2,
    "最大値":877.0,
    "最小値":213.0,
    "中央値":445.0,
    "標準偏差":97.2,
    "分散":9451.7,
    "近似曲線_値":487.011,
    "移動平均_7日":522.9,
    "移動平均_14日":519.4,
    "移動平均_30日":530.5,
    "平均(同日)":450.6,
    "中央値(同日)":447.0,
    "比率-(移動平均7日\/近似曲線_値)":7.4,
    "比率-(移動平均7日\/中央値)":17.5,
    "前年同日比(移動平均7日)":-3.9,
    "前年同日比(移動平均14日)":-3.0,
    "前年同日比(移動平均30日)":-4.8
  },
  {
    "品目コード":"39000",
    "品目名":"その他の野菜",
    "日付":"2026-02-27",
    "価格":1065.0,
    "平均":836.1,
    "最大値":1658.0,
    "最小値":177.0,
    "中央値":826.0,
    "標準偏差":164.2,
    "分散":26958.2,
    "近似曲線_値":953.531,
    "移動平均_7日":952.0,
    "移動平均_14日":970.1,
    "移動平均_30日":966.9,
    "平均(同日)":845.7,
    "中央値(同日)":828.0,
    "比率-(移動平均7日\/近似曲線_値)":-0.2,
    "比率-(移動平均7日\/中央値)":15.3,
    "前年同日比(移動平均7日)":-1.5,
    "前年同日比(移動平均14日)":-0.5,
    "前年同日比(移動平均30日)":-0.1
  }
]