[
  {
    "品目コード":"30000",
    "品目名":"野菜総計",
    "日付":"2026-06-19",
    "価格":276.0,
    "平均":245.5,
    "最大値":458.0,
    "最小値":142.0,
    "中央値":242.0,
    "標準偏差":35.4,
    "分散":1252.5,
    "近似曲線_値":270.266,
    "移動平均_7日":278.7,
    "移動平均_14日":273.2,
    "移動平均_30日":265.5,
    "平均(同日)":245.1,
    "中央値(同日)":243.0,
    "比率-(移動平均7日\/近似曲線_値)":3.1,
    "比率-(移動平均7日\/中央値)":15.2,
    "前年同日比(移動平均7日)":4.9,
    "前年同日比(移動平均14日)":2.9,
    "前年同日比(移動平均30日)":3.5
  },
  {
    "品目コード":"30100",
    "品目名":"だいこん",
    "日付":"2026-06-19",
    "価格":108.0,
    "平均":98.2,
    "最大値":363.0,
    "最小値":44.0,
    "中央値":93.0,
    "標準偏差":28.8,
    "分散":826.7,
    "近似曲線_値":105.629,
    "移動平均_7日":109.3,
    "移動平均_14日":105.4,
    "移動平均_30日":105.2,
    "平均(同日)":102.8,
    "中央値(同日)":103.0,
    "比率-(移動平均7日\/近似曲線_値)":3.5,
    "比率-(移動平均7日\/中央値)":17.5,
    "前年同日比(移動平均7日)":-7.1,
    "前年同日比(移動平均14日)":-11.7,
    "前年同日比(移動平均30日)":-5.1
  },
  {
    "品目コード":"30200",
    "品目名":"かぶ",
    "日付":"2026-06-19",
    "価格":153.0,
    "平均":160.8,
    "最大値":984.0,
    "最小値":66.0,
    "中央値":150.0,
    "標準偏差":51.1,
    "分散":2607.4,
    "近似曲線_値":163.272,
    "移動平均_7日":162.9,
    "移動平均_14日":160.8,
    "移動平均_30日":154.6,
    "平均(同日)":142.0,
    "中央値(同日)":142.0,
    "比率-(移動平均7日\/近似曲線_値)":-0.2,
    "比率-(移動平均7日\/中央値)":8.6,
    "前年同日比(移動平均7日)":1.4,
    "前年同日比(移動平均14日)":0.0,
    "前年同日比(移動平均30日)":0.5
  },
  {
    "品目コード":"30300",
    "品目名":"にんじん",
    "日付":"2026-06-19",
    "価格":164.0,
    "平均":149.9,
    "最大値":336.0,
    "最小値":48.0,
    "中央値":139.0,
    "標準偏差":47.2,
    "分散":2223.1,
    "近似曲線_値":170.745,
    "移動平均_7日":166.6,
    "移動平均_14日":166.3,
    "移動平均_30日":153.7,
    "平均(同日)":145.7,
    "中央値(同日)":134.0,
    "比率-(移動平均7日\/近似曲線_値)":-2.4,
    "比率-(移動平均7日\/中央値)":19.9,
    "前年同日比(移動平均7日)":-8.5,
    "前年同日比(移動平均14日)":-5.5,
    "前年同日比(移動平均30日)":-4.5
  },
  {
    "品目コード":"30400",
    "品目名":"ごぼう",
    "日付":"2026-06-19",
    "価格":371.0,
    "平均":326.0,
    "最大値":679.0,
    "最小値":111.0,
    "中央値":317.0,
    "標準偏差":84.6,
    "分散":7159.5,
    "近似曲線_値":377.65,
    "移動平均_7日":369.9,
    "移動平均_14日":378.6,
    "移動平均_30日":380.5,
    "平均(同日)":372.9,
    "中央値(同日)":377.0,
    "比率-(移動平均7日\/近似曲線_値)":-2.1,
    "比率-(移動平均7日\/中央値)":16.7,
    "前年同日比(移動平均7日)":-25.9,
    "前年同日比(移動平均14日)":-24.3,
    "前年同日比(移動平均30日)":-24.5
  },
  {
    "品目コード":"30500",
    "品目名":"たけのこ",
    "日付":"2026-06-19",
    "価格":550.0,
    "平均":1030.6,
    "最大値":8694.0,
    "最小値":4.0,
    "中央値":823.0,
    "標準偏差":759.9,
    "分散":577414.2,
    "近似曲線_値":1394.264,
    "移動平均_7日":343.9,
    "移動平均_14日":357.8,
    "移動平均_30日":436.5,
    "平均(同日)":455.1,
    "中央値(同日)":410.0,
    "比率-(移動平均7日\/近似曲線_値)":-75.3,
    "比率-(移動平均7日\/中央値)":-58.2,
    "前年同日比(移動平均7日)":-10.7,
    "前年同日比(移動平均14日)":-13.7,
    "前年同日比(移動平均30日)":-10.1
  },
  {
    "品目コード":"30600",
    "品目名":"れんこん",
    "日付":"2026-06-19",
    "価格":1116.0,
    "平均":572.3,
    "最大値":1778.0,
    "最小値":27.0,
    "中央値":490.0,
    "標準偏差":245.4,
    "分散":60208.9,
    "近似曲線_値":495.707,
    "移動平均_7日":1118.9,
    "移動平均_14日":1091.4,
    "移動平均_30日":902.0,
    "平均(同日)":1131.4,
    "中央値(同日)":1116.0,
    "比率-(移動平均7日\/近似曲線_値)":125.7,
    "比率-(移動平均7日\/中央値)":128.3,
    "前年同日比(移動平均7日)":-6.1,
    "前年同日比(移動平均14日)":-8.8,
    "前年同日比(移動平均30日)":-10.2
  },
  {
    "品目コード":"31100",
    "品目名":"はくさい",
    "日付":"2026-06-19",
    "価格":91.0,
    "平均":83.6,
    "最大値":342.0,
    "最小値":25.0,
    "中央値":75.0,
    "標準偏差":34.9,
    "分散":1219.7,
    "近似曲線_値":82.43,
    "移動平均_7日":90.9,
    "移動平均_14日":83.3,
    "移動平均_30日":73.3,
    "平均(同日)":73.4,
    "中央値(同日)":73.0,
    "比率-(移動平均7日\/近似曲線_値)":10.3,
    "比率-(移動平均7日\/中央値)":21.2,
    "前年同日比(移動平均7日)":24.5,
    "前年同日比(移動平均14日)":15.2,
    "前年同日比(移動平均30日)":13.5
  },
  {
    "品目コード":"31300",
    "品目名":"みずな",
    "日付":"2026-06-19",
    "価格":330.0,
    "平均":401.4,
    "最大値":1576.0,
    "最小値":187.0,
    "中央値":369.0,
    "標準偏差":148.9,
    "分散":22158.6,
    "近似曲線_値":388.032,
    "移動平均_7日":322.1,
    "移動平均_14日":314.6,
    "移動平均_30日":298.4,
    "平均(同日)":307.4,
    "中央値(同日)":293.0,
    "比率-(移動平均7日\/近似曲線_値)":-17.0,
    "比率-(移動平均7日\/中央値)":-12.7,
    "前年同日比(移動平均7日)":9.3,
    "前年同日比(移動平均14日)":3.1,
    "前年同日比(移動平均30日)":2.3
  },
  {
    "品目コード":"31500",
    "品目名":"こまつな",
    "日付":"2026-06-19",
    "価格":311.0,
    "平均":332.4,
    "最大値":922.0,
    "最小値":84.0,
    "中央値":311.0,
    "標準偏差":117.1,
    "分散":13714.0,
    "近似曲線_値":327.891,
    "移動平均_7日":304.9,
    "移動平均_14日":290.9,
    "移動平均_30日":284.0,
    "平均(同日)":274.1,
    "中央値(同日)":263.0,
    "比率-(移動平均7日\/近似曲線_値)":-7.0,
    "比率-(移動平均7日\/中央値)":-2.0,
    "前年同日比(移動平均7日)":13.0,
    "前年同日比(移動平均14日)":5.4,
    "前年同日比(移動平均30日)":10.2
  },
  {
    "品目コード":"31550",
    "品目名":"その他の菜類",
    "日付":"2026-06-19",
    "価格":615.0,
    "平均":426.5,
    "最大値":1377.0,
    "最小値":142.0,
    "中央値":405.0,
    "標準偏差":111.5,
    "分散":12429.5,
    "近似曲線_値":476.22,
    "移動平均_7日":615.6,
    "移動平均_14日":576.1,
    "移動平均_30日":520.7,
    "平均(同日)":480.5,
    "中央値(同日)":462.0,
    "比率-(移動平均7日\/近似曲線_値)":29.3,
    "比率-(移動平均7日\/中央値)":52.0,
    "前年同日比(移動平均7日)":13.6,
    "前年同日比(移動平均14日)":11.2,
    "前年同日比(移動平均30日)":3.9
  },
  {
    "品目コード":"31560",
    "品目名":"ちんげんさい",
    "日付":"2026-06-19",
    "価格":334.0,
    "平均":334.9,
    "最大値":878.0,
    "最小値":118.0,
    "中央値":321.0,
    "標準偏差":86.5,
    "分散":7477.3,
    "近似曲線_値":361.622,
    "移動平均_7日":336.0,
    "移動平均_14日":327.7,
    "移動平均_30日":318.7,
    "平均(同日)":283.1,
    "中央値(同日)":277.0,
    "比率-(移動平均7日\/近似曲線_値)":-7.1,
    "比率-(移動平均7日\/中央値)":4.7,
    "前年同日比(移動平均7日)":5.3,
    "前年同日比(移動平均14日)":2.2,
    "前年同日比(移動平均30日)":3.6
  },
  {
    "品目コード":"31700",
    "品目名":"キャベツ",
    "日付":"2026-06-19",
    "価格":93.0,
    "平均":100.0,
    "最大値":407.0,
    "最小値":17.0,
    "中央値":90.0,
    "標準偏差":40.7,
    "分散":1657.8,
    "近似曲線_値":106.359,
    "移動平均_7日":91.9,
    "移動平均_14日":92.8,
    "移動平均_30日":97.3,
    "平均(同日)":88.3,
    "中央値(同日)":89.0,
    "比率-(移動平均7日\/近似曲線_値)":-13.6,
    "比率-(移動平均7日\/中央値)":2.1,
    "前年同日比(移動平均7日)":23.2,
    "前年同日比(移動平均14日)":27.3,
    "前年同日比(移動平均30日)":37.2
  },
  {
    "品目コード":"31800",
    "品目名":"ほうれんそう",
    "日付":"2026-06-19",
    "価格":567.0,
    "平均":617.6,
    "最大値":1944.0,
    "最小値":151.0,
    "中央値":553.0,
    "標準偏差":205.4,
    "分散":42206.8,
    "近似曲線_値":628.228,
    "移動平均_7日":552.3,
    "移動平均_14日":547.0,
    "移動平均_30日":533.9,
    "平均(同日)":527.2,
    "中央値(同日)":525.0,
    "比率-(移動平均7日\/近似曲線_値)":-12.1,
    "比率-(移動平均7日\/中央値)":-0.1,
    "前年同日比(移動平均7日)":4.7,
    "前年同日比(移動平均14日)":2.2,
    "前年同日比(移動平均30日)":2.7
  },
  {
    "品目コード":"31900",
    "品目名":"ねぎ",
    "日付":"2026-06-19",
    "価格":460.0,
    "平均":435.7,
    "最大値":1143.0,
    "最小値":186.0,
    "中央値":432.0,
    "標準偏差":85.4,
    "分散":7300.5,
    "近似曲線_値":463.449,
    "移動平均_7日":465.7,
    "移動平均_14日":471.4,
    "移動平均_30日":470.6,
    "平均(同日)":456.9,
    "中央値(同日)":454.0,
    "比率-(移動平均7日\/近似曲線_値)":0.5,
    "比率-(移動平均7日\/中央値)":7.8,
    "前年同日比(移動平均7日)":-0.7,
    "前年同日比(移動平均14日)":1.9,
    "前年同日比(移動平均30日)":5.4
  },
  {
    "品目コード":"32300",
    "品目名":"ふき",
    "日付":"2026-06-19",
    "価格":328.0,
    "平均":386.8,
    "最大値":1563.0,
    "最小値":24.0,
    "中央値":353.0,
    "標準偏差":221.7,
    "分散":49130.0,
    "近似曲線_値":464.742,
    "移動平均_7日":315.0,
    "移動平均_14日":300.9,
    "移動平均_30日":337.4,
    "平均(同日)":289.2,
    "中央値(同日)":262.0,
    "比率-(移動平均7日\/近似曲線_値)":-32.2,
    "比率-(移動平均7日\/中央値)":-10.8,
    "前年同日比(移動平均7日)":-1.5,
    "前年同日比(移動平均14日)":-9.6,
    "前年同日比(移動平均30日)":0.6
  },
  {
    "品目コード":"32400",
    "品目名":"うど",
    "日付":"2025-12-28",
    "価格":603.0,
    "平均":694.6,
    "最大値":3645.0,
    "最小値":189.0,
    "中央値":644.0,
    "標準偏差":246.7,
    "分散":60882.7,
    "近似曲線_値":806.318,
    "移動平均_7日":720.7,
    "移動平均_14日":731.9,
    "移動平均_30日":732.9,
    "平均(同日)":684.2,
    "中央値(同日)":655.5,
    "比率-(移動平均7日\/近似曲線_値)":-10.6,
    "比率-(移動平均7日\/中央値)":11.9,
    "前年同日比(移動平均7日)":-19.8,
    "前年同日比(移動平均14日)":-19.9,
    "前年同日比(移動平均30日)":-23.9
  },
  {
    "品目コード":"32500",
    "品目名":"みつば",
    "日付":"2026-06-19",
    "価格":579.0,
    "平均":650.4,
    "最大値":2916.0,
    "最小値":290.0,
    "中央値":560.0,
    "標準偏差":296.0,
    "分散":87630.2,
    "近似曲線_値":721.937,
    "移動平均_7日":587.6,
    "移動平均_14日":576.6,
    "移動平均_30日":556.6,
    "平均(同日)":444.5,
    "中央値(同日)":435.0,
    "比率-(移動平均7日\/近似曲線_値)":-18.6,
    "比率-(移動平均7日\/中央値)":4.9,
    "前年同日比(移動平均7日)":15.0,
    "前年同日比(移動平均14日)":13.1,
    "前年同日比(移動平均30日)":9.8
  },
  {
    "品目コード":"32600",
    "品目名":"しゅんぎく",
    "日付":"2026-06-19",
    "価格":828.0,
    "平均":799.4,
    "最大値":2098.0,
    "最小値":58.0,
    "中央値":686.0,
    "標準偏差":354.1,
    "分散":125413.4,
    "近似曲線_値":926.001,
    "移動平均_7日":811.1,
    "移動平均_14日":764.2,
    "移動平均_30日":671.2,
    "平均(同日)":616.5,
    "中央値(同日)":582.0,
    "比率-(移動平均7日\/近似曲線_値)":-12.4,
    "比率-(移動平均7日\/中央値)":18.2,
    "前年同日比(移動平均7日)":9.7,
    "前年同日比(移動平均14日)":0.7,
    "前年同日比(移動平均30日)":-6.9
  },
  {
    "品目コード":"32800",
    "品目名":"にら",
    "日付":"2026-06-19",
    "価格":505.0,
    "平均":727.4,
    "最大値":2464.0,
    "最小値":175.0,
    "中央値":720.0,
    "標準偏差":242.6,
    "分散":58855.5,
    "近似曲線_値":788.996,
    "移動平均_7日":484.4,
    "移動平均_14日":463.6,
    "移動平均_30日":452.8,
    "平均(同日)":476.6,
    "中央値(同日)":475.0,
    "比率-(移動平均7日\/近似曲線_値)":-38.6,
    "比率-(移動平均7日\/中央値)":-32.7,
    "前年同日比(移動平均7日)":13.2,
    "前年同日比(移動平均14日)":10.7,
    "前年同日比(移動平均30日)":10.9
  },
  {
    "品目コード":"32900",
    "品目名":"セルリー",
    "日付":"2026-06-19",
    "価格":272.0,
    "平均":274.0,
    "最大値":600.0,
    "最小値":66.0,
    "中央値":274.0,
    "標準偏差":59.2,
    "分散":3510.0,
    "近似曲線_値":284.224,
    "移動平均_7日":268.0,
    "移動平均_14日":269.4,
    "移動平均_30日":300.9,
    "平均(同日)":274.8,
    "中央値(同日)":272.0,
    "比率-(移動平均7日\/近似曲線_値)":-5.7,
    "比率-(移動平均7日\/中央値)":-2.2,
    "前年同日比(移動平均7日)":-2.2,
    "前年同日比(移動平均14日)":-3.3,
    "前年同日比(移動平均30日)":2.2
  },
  {
    "品目コード":"33100",
    "品目名":"アスパラガス",
    "日付":"2026-06-19",
    "価格":1057.0,
    "平均":1307.2,
    "最大値":3562.0,
    "最小値":72.0,
    "中央値":1259.0,
    "標準偏差":371.1,
    "分散":137687.5,
    "近似曲線_値":1572.024,
    "移動平均_7日":1538.7,
    "移動平均_14日":1549.9,
    "移動平均_30日":1692.1,
    "平均(同日)":1334.2,
    "中央値(同日)":1315.0,
    "比率-(移動平均7日\/近似曲線_値)":-2.1,
    "比率-(移動平均7日\/中央値)":22.2,
    "前年同日比(移動平均7日)":-7.6,
    "前年同日比(移動平均14日)":-9.0,
    "前年同日比(移動平均30日)":-4.2
  },
  {
    "品目コード":"33200",
    "品目名":"カリフラワー",
    "日付":"2026-06-19",
    "価格":350.0,
    "平均":274.3,
    "最大値":1215.0,
    "最小値":51.0,
    "中央値":261.0,
    "標準偏差":82.2,
    "分散":6762.4,
    "近似曲線_値":264.914,
    "移動平均_7日":322.9,
    "移動平均_14日":291.7,
    "移動平均_30日":277.6,
    "平均(同日)":287.3,
    "中央値(同日)":289.0,
    "比率-(移動平均7日\/近似曲線_値)":21.9,
    "比率-(移動平均7日\/中央値)":23.7,
    "前年同日比(移動平均7日)":32.0,
    "前年同日比(移動平均14日)":7.8,
    "前年同日比(移動平均30日)":4.7
  },
  {
    "品目コード":"33300",
    "品目名":"ブロッコリー",
    "日付":"2026-06-19",
    "価格":546.0,
    "平均":439.1,
    "最大値":949.0,
    "最小値":106.0,
    "中央値":434.0,
    "標準偏差":111.3,
    "分散":12390.0,
    "近似曲線_値":455.55,
    "移動平均_7日":557.7,
    "移動平均_14日":550.8,
    "移動平均_30日":511.1,
    "平均(同日)":479.4,
    "中央値(同日)":471.0,
    "比率-(移動平均7日\/近似曲線_値)":22.4,
    "比率-(移動平均7日\/中央値)":28.5,
    "前年同日比(移動平均7日)":19.8,
    "前年同日比(移動平均14日)":12.3,
    "前年同日比(移動平均30日)":16.3
  },
  {
    "品目コード":"33400",
    "品目名":"レタス",
    "日付":"2026-06-19",
    "価格":162.0,
    "平均":201.5,
    "最大値":726.0,
    "最小値":36.0,
    "中央値":183.0,
    "標準偏差":81.4,
    "分散":6622.6,
    "近似曲線_値":196.948,
    "移動平均_7日":162.6,
    "移動平均_14日":156.4,
    "移動平均_30日":162.1,
    "平均(同日)":133.8,
    "中央値(同日)":132.0,
    "比率-(移動平均7日\/近似曲線_値)":-17.4,
    "比率-(移動平均7日\/中央値)":-11.1,
    "前年同日比(移動平均7日)":12.2,
    "前年同日比(移動平均14日)":8.3,
    "前年同日比(移動平均30日)":21.8
  },
  {
    "品目コード":"33600",
    "品目名":"パセリ",
    "日付":"2025-12-28",
    "価格":1973.0,
    "平均":1539.1,
    "最大値":11751.0,
    "最小値":54.0,
    "中央値":1229.0,
    "標準偏差":945.8,
    "分散":894621.0,
    "近似曲線_値":1976.706,
    "移動平均_7日":2049.7,
    "移動平均_14日":2035.2,
    "移動平均_30日":1845.5,
    "平均(同日)":2333.0,
    "中央値(同日)":2074.5,
    "比率-(移動平均7日\/近似曲線_値)":3.7,
    "比率-(移動平均7日\/中央値)":66.8,
    "前年同日比(移動平均7日)":-51.1,
    "前年同日比(移動平均14日)":-44.4,
    "前年同日比(移動平均30日)":-40.5
  },
  {
    "品目コード":"34100",
    "品目名":"きゅうり",
    "日付":"2026-06-19",
    "価格":361.0,
    "平均":358.0,
    "最大値":1040.0,
    "最小値":132.0,
    "中央値":339.0,
    "標準偏差":116.0,
    "分散":13456.3,
    "近似曲線_値":392.925,
    "移動平均_7日":361.3,
    "移動平均_14日":338.8,
    "移動平均_30日":293.0,
    "平均(同日)":272.6,
    "中央値(同日)":254.0,
    "比率-(移動平均7日\/近似曲線_値)":-8.0,
    "比率-(移動平均7日\/中央値)":6.6,
    "前年同日比(移動平均7日)":16.5,
    "前年同日比(移動平均14日)":8.4,
    "前年同日比(移動平均30日)":-2.2
  },
  {
    "品目コード":"34200",
    "品目名":"かぼちゃ",
    "日付":"2026-06-19",
    "価格":319.0,
    "平均":224.4,
    "最大値":1100.0,
    "最小値":95.0,
    "中央値":208.0,
    "標準偏差":84.2,
    "分散":7088.7,
    "近似曲線_値":280.57,
    "移動平均_7日":324.0,
    "移動平均_14日":315.9,
    "移動平均_30日":310.5,
    "平均(同日)":231.5,
    "中央値(同日)":229.0,
    "比率-(移動平均7日\/近似曲線_値)":15.5,
    "比率-(移動平均7日\/中央値)":55.8,
    "前年同日比(移動平均7日)":13.7,
    "前年同日比(移動平均14日)":12.9,
    "前年同日比(移動平均30日)":19.5
  },
  {
    "品目コード":"34300",
    "品目名":"なす",
    "日付":"2026-06-19",
    "価格":394.0,
    "平均":402.5,
    "最大値":926.0,
    "最小値":95.0,
    "中央値":399.0,
    "標準偏差":78.3,
    "分散":6127.9,
    "近似曲線_値":411.417,
    "移動平均_7日":408.3,
    "移動平均_14日":403.4,
    "移動平均_30日":387.3,
    "平均(同日)":372.8,
    "中央値(同日)":376.0,
    "比率-(移動平均7日\/近似曲線_値)":-0.8,
    "比率-(移動平均7日\/中央値)":2.3,
    "前年同日比(移動平均7日)":-0.1,
    "前年同日比(移動平均14日)":-0.7,
    "前年同日比(移動平均30日)":1.1
  },
  {
    "品目コード":"34400",
    "品目名":"トマト",
    "日付":"2026-06-19",
    "価格":403.0,
    "平均":405.7,
    "最大値":1147.0,
    "最小値":146.0,
    "中央値":378.0,
    "標準偏差":126.5,
    "分散":15996.2,
    "近似曲線_値":461.493,
    "移動平均_7日":395.7,
    "移動平均_14日":387.7,
    "移動平均_30日":381.1,
    "平均(同日)":314.0,
    "中央値(同日)":316.0,
    "比率-(移動平均7日\/近似曲線_値)":-14.3,
    "比率-(移動平均7日\/中央値)":4.7,
    "前年同日比(移動平均7日)":17.0,
    "前年同日比(移動平均14日)":14.0,
    "前年同日比(移動平均30日)":16.1
  },
  {
    "品目コード":"34450",
    "品目名":"ミニトマト",
    "日付":"2026-06-19",
    "価格":597.0,
    "平均":694.6,
    "最大値":1760.0,
    "最小値":326.0,
    "中央値":656.0,
    "標準偏差":201.5,
    "分散":40619.6,
    "近似曲線_値":716.88,
    "移動平均_7日":591.4,
    "移動平均_14日":577.0,
    "移動平均_30日":561.5,
    "平均(同日)":529.6,
    "中央値(同日)":543.0,
    "比率-(移動平均7日\/近似曲線_値)":-17.5,
    "比率-(移動平均7日\/中央値)":-9.8,
    "前年同日比(移動平均7日)":18.2,
    "前年同日比(移動平均14日)":19.2,
    "前年同日比(移動平均30日)":21.0
  },
  {
    "品目コード":"34500",
    "品目名":"ピーマン",
    "日付":"2026-06-19",
    "価格":455.0,
    "平均":516.5,
    "最大値":1113.0,
    "最小値":173.0,
    "中央値":499.0,
    "標準偏差":143.4,
    "分散":20569.0,
    "近似曲線_値":594.439,
    "移動平均_7日":426.1,
    "移動平均_14日":420.1,
    "移動平均_30日":456.0,
    "平均(同日)":425.3,
    "中央値(同日)":411.0,
    "比率-(移動平均7日\/近似曲線_値)":-28.3,
    "比率-(移動平均7日\/中央値)":-14.6,
    "前年同日比(移動平均7日)":-22.6,
    "前年同日比(移動平均14日)":-16.4,
    "前年同日比(移動平均30日)":3.4
  },
  {
    "品目コード":"34600",
    "品目名":"ししとう",
    "日付":"2026-06-19",
    "価格":1435.0,
    "平均":1488.3,
    "最大値":5130.0,
    "最小値":324.0,
    "中央値":1365.0,
    "標準偏差":507.7,
    "分散":257809.2,
    "近似曲線_値":1790.288,
    "移動平均_7日":1384.9,
    "移動平均_14日":1359.5,
    "移動平均_30日":1410.4,
    "平均(同日)":1130.5,
    "中央値(同日)":1107.0,
    "比率-(移動平均7日\/近似曲線_値)":-22.6,
    "比率-(移動平均7日\/中央値)":1.5,
    "前年同日比(移動平均7日)":6.4,
    "前年同日比(移動平均14日)":1.5,
    "前年同日比(移動平均30日)":6.1
  },
  {
    "品目コード":"34700",
    "品目名":"スイトコーン",
    "日付":"2026-06-19",
    "価格":345.0,
    "平均":361.9,
    "最大値":1813.0,
    "最小値":16.0,
    "中央値":333.0,
    "標準偏差":137.4,
    "分散":18868.6,
    "近似曲線_値":433.632,
    "移動平均_7日":310.0,
    "移動平均_14日":299.8,
    "移動平均_30日":352.0,
    "平均(同日)":278.5,
    "中央値(同日)":271.0,
    "比率-(移動平均7日\/近似曲線_値)":-28.5,
    "比率-(移動平均7日\/中央値)":-6.9,
    "前年同日比(移動平均7日)":-3.9,
    "前年同日比(移動平均14日)":-16.2,
    "前年同日比(移動平均30日)":-10.6
  },
  {
    "品目コード":"35100",
    "品目名":"さやいんげん",
    "日付":"2026-06-19",
    "価格":1007.0,
    "平均":1008.0,
    "最大値":2528.0,
    "最小値":180.0,
    "中央値":953.0,
    "標準偏差":261.6,
    "分散":68433.4,
    "近似曲線_値":1156.771,
    "移動平均_7日":961.6,
    "移動平均_14日":910.6,
    "移動平均_30日":883.4,
    "平均(同日)":818.2,
    "中央値(同日)":829.0,
    "比率-(移動平均7日\/近似曲線_値)":-16.9,
    "比率-(移動平均7日\/中央値)":0.9,
    "前年同日比(移動平均7日)":27.3,
    "前年同日比(移動平均14日)":12.7,
    "前年同日比(移動平均30日)":6.2
  },
  {
    "品目コード":"35200",
    "品目名":"さやえんどう",
    "日付":"2026-06-19",
    "価格":1960.0,
    "平均":1553.1,
    "最大値":6638.0,
    "最小値":621.0,
    "中央値":1356.0,
    "標準偏差":617.7,
    "分散":381526.9,
    "近似曲線_値":1694.77,
    "移動平均_7日":1765.0,
    "移動平均_14日":1632.6,
    "移動平均_30日":1415.9,
    "平均(同日)":1451.8,
    "中央値(同日)":1453.0,
    "比率-(移動平均7日\/近似曲線_値)":4.1,
    "比率-(移動平均7日\/中央値)":30.2,
    "前年同日比(移動平均7日)":15.0,
    "前年同日比(移動平均14日)":13.5,
    "前年同日比(移動平均30日)":12.7
  },
  {
    "品目コード":"35300",
    "品目名":"実えんどう",
    "日付":"2026-06-19",
    "価格":980.0,
    "平均":853.0,
    "最大値":5184.0,
    "最小値":108.0,
    "中央値":893.0,
    "標準偏差":356.0,
    "分散":126708.4,
    "近似曲線_値":904.606,
    "移動平均_7日":991.9,
    "移動平均_14日":952.4,
    "移動平均_30日":960.2,
    "平均(同日)":867.5,
    "中央値(同日)":892.0,
    "比率-(移動平均7日\/近似曲線_値)":9.6,
    "比率-(移動平均7日\/中央値)":11.1,
    "前年同日比(移動平均7日)":15.5,
    "前年同日比(移動平均14日)":22.2,
    "前年同日比(移動平均30日)":21.4
  },
  {
    "品目コード":"35400",
    "品目名":"そらまめ",
    "日付":"2026-06-19",
    "価格":716.0,
    "平均":726.8,
    "最大値":2990.0,
    "最小値":1.0,
    "中央値":648.0,
    "標準偏差":352.9,
    "分散":124525.3,
    "近似曲線_値":689.176,
    "移動平均_7日":719.6,
    "移動平均_14日":646.7,
    "移動平均_30日":592.3,
    "平均(同日)":611.0,
    "中央値(同日)":572.0,
    "比率-(移動平均7日\/近似曲線_値)":4.4,
    "比率-(移動平均7日\/中央値)":11.0,
    "前年同日比(移動平均7日)":11.8,
    "前年同日比(移動平均14日)":4.3,
    "前年同日比(移動平均30日)":5.5
  },
  {
    "品目コード":"35500",
    "品目名":"えだまめ",
    "日付":"2026-06-19",
    "価格":1146.0,
    "平均":1341.8,
    "最大値":2952.0,
    "最小値":54.0,
    "中央値":1085.0,
    "標準偏差":642.3,
    "分散":412506.9,
    "近似曲線_値":1583.322,
    "移動平均_7日":1132.7,
    "移動平均_14日":1139.9,
    "移動平均_30日":1242.7,
    "平均(同日)":1002.2,
    "中央値(同日)":1010.0,
    "比率-(移動平均7日\/近似曲線_値)":-28.5,
    "比率-(移動平均7日\/中央値)":4.4,
    "前年同日比(移動平均7日)":2.6,
    "前年同日比(移動平均14日)":-1.9,
    "前年同日比(移動平均30日)":-2.0
  },
  {
    "品目コード":"36100",
    "品目名":"かんしょ",
    "日付":"2026-06-19",
    "価格":322.0,
    "平均":273.7,
    "最大値":468.0,
    "最小値":89.0,
    "中央値":275.0,
    "標準偏差":44.2,
    "分散":1949.2,
    "近似曲線_値":315.539,
    "移動平均_7日":330.7,
    "移動平均_14日":333.0,
    "移動平均_30日":332.7,
    "平均(同日)":316.3,
    "中央値(同日)":322.0,
    "比率-(移動平均7日\/近似曲線_値)":4.8,
    "比率-(移動平均7日\/中央値)":20.3,
    "前年同日比(移動平均7日)":-10.6,
    "前年同日比(移動平均14日)":-10.6,
    "前年同日比(移動平均30日)":-10.2
  },
  {
    "品目コード":"36200",
    "品目名":"ばれいしょ",
    "日付":"2026-06-19",
    "価格":187.0,
    "平均":170.7,
    "最大値":452.0,
    "最小値":59.0,
    "中央値":154.0,
    "標準偏差":65.3,
    "分散":4263.4,
    "近似曲線_値":206.825,
    "移動平均_7日":189.1,
    "移動平均_14日":172.4,
    "移動平均_30日":157.7,
    "平均(同日)":169.5,
    "中央値(同日)":148.0,
    "比率-(移動平均7日\/近似曲線_値)":-8.6,
    "比率-(移動平均7日\/中央値)":22.8,
    "前年同日比(移動平均7日)":19.7,
    "前年同日比(移動平均14日)":2.0,
    "前年同日比(移動平均30日)":-15.1
  },
  {
    "品目コード":"36300",
    "品目名":"さといも",
    "日付":"2026-06-19",
    "価格":578.0,
    "平均":368.1,
    "最大値":1111.0,
    "最小値":5.0,
    "中央値":346.0,
    "標準偏差":100.0,
    "分散":9996.8,
    "近似曲線_値":428.429,
    "移動平均_7日":554.0,
    "移動平均_14日":548.4,
    "移動平均_30日":555.9,
    "平均(同日)":533.0,
    "中央値(同日)":553.0,
    "比率-(移動平均7日\/近似曲線_値)":29.3,
    "比率-(移動平均7日\/中央値)":60.1,
    "前年同日比(移動平均7日)":-29.6,
    "前年同日比(移動平均14日)":-33.5,
    "前年同日比(移動平均30日)":-27.9
  },
  {
    "品目コード":"36500",
    "品目名":"やまのいも",
    "日付":"2026-06-19",
    "価格":419.0,
    "平均":389.1,
    "最大値":855.0,
    "最小値":54.0,
    "中央値":382.0,
    "標準偏差":79.4,
    "分散":6302.2,
    "近似曲線_値":396.772,
    "移動平均_7日":412.1,
    "移動平均_14日":412.9,
    "移動平均_30日":411.3,
    "平均(同日)":383.8,
    "中央値(同日)":393.0,
    "比率-(移動平均7日\/近似曲線_値)":3.9,
    "比率-(移動平均7日\/中央値)":7.9,
    "前年同日比(移動平均7日)":-0.9,
    "前年同日比(移動平均14日)":0.0,
    "前年同日比(移動平均30日)":-0.3
  },
  {
    "品目コード":"36610",
    "品目名":"たまねぎ",
    "日付":"2026-06-19",
    "価格":126.0,
    "平均":123.4,
    "最大値":453.0,
    "最小値":42.0,
    "中央値":110.0,
    "標準偏差":46.0,
    "分散":2114.8,
    "近似曲線_値":165.282,
    "移動平均_7日":120.3,
    "移動平均_14日":111.1,
    "移動平均_30日":103.9,
    "平均(同日)":120.9,
    "中央値(同日)":103.0,
    "比率-(移動平均7日\/近似曲線_値)":-27.2,
    "比率-(移動平均7日\/中央値)":9.4,
    "前年同日比(移動平均7日)":-11.6,
    "前年同日比(移動平均14日)":-21.5,
    "前年同日比(移動平均30日)":-27.9
  },
  {
    "品目コード":"36700",
    "品目名":"にんにく",
    "日付":"2026-06-19",
    "価格":925.0,
    "平均":1009.5,
    "最大値":1846.0,
    "最小値":278.0,
    "中央値":1003.0,
    "標準偏差":231.9,
    "分散":53764.7,
    "近似曲線_値":1080.376,
    "移動平均_7日":1100.3,
    "移動平均_14日":1120.0,
    "移動平均_30日":1168.8,
    "平均(同日)":918.6,
    "中央値(同日)":892.0,
    "比率-(移動平均7日\/近似曲線_値)":1.8,
    "比率-(移動平均7日\/中央値)":9.7,
    "前年同日比(移動平均7日)":-15.1,
    "前年同日比(移動平均14日)":-9.7,
    "前年同日比(移動平均30日)":-7.3
  },
  {
    "品目コード":"37200",
    "品目名":"しょうが",
    "日付":"2026-06-19",
    "価格":850.0,
    "平均":720.1,
    "最大値":1337.0,
    "最小値":234.0,
    "中央値":669.0,
    "標準偏差":160.6,
    "分散":25806.9,
    "近似曲線_値":820.432,
    "移動平均_7日":860.9,
    "移動平均_14日":888.2,
    "移動平均_30日":975.5,
    "平均(同日)":746.7,
    "中央値(同日)":778.0,
    "比率-(移動平均7日\/近似曲線_値)":4.9,
    "比率-(移動平均7日\/中央値)":28.7,
    "前年同日比(移動平均7日)":-2.0,
    "前年同日比(移動平均14日)":0.0,
    "前年同日比(移動平均30日)":4.5
  },
  {
    "品目コード":"38100",
    "品目名":"生しいたけ",
    "日付":"2026-06-19",
    "価格":934.0,
    "平均":966.9,
    "最大値":2341.0,
    "最小値":354.0,
    "中央値":949.0,
    "標準偏差":145.7,
    "分散":21214.0,
    "近似曲線_値":1005.149,
    "移動平均_7日":939.6,
    "移動平均_14日":943.4,
    "移動平均_30日":945.8,
    "平均(同日)":851.5,
    "中央値(同日)":840.0,
    "比率-(移動平均7日\/近似曲線_値)":-6.5,
    "比率-(移動平均7日\/中央値)":-1.0,
    "前年同日比(移動平均7日)":2.5,
    "前年同日比(移動平均14日)":1.8,
    "前年同日比(移動平均30日)":2.1
  },
  {
    "品目コード":"38300",
    "品目名":"なめこ",
    "日付":"2026-06-19",
    "価格":456.0,
    "平均":465.0,
    "最大値":1026.0,
    "最小値":291.0,
    "中央値":459.0,
    "標準偏差":65.9,
    "分散":4337.6,
    "近似曲線_値":484.609,
    "移動平均_7日":469.1,
    "移動平均_14日":469.1,
    "移動平均_30日":477.9,
    "平均(同日)":426.0,
    "中央値(同日)":417.0,
    "比率-(移動平均7日\/近似曲線_値)":-3.2,
    "比率-(移動平均7日\/中央値)":2.2,
    "前年同日比(移動平均7日)":4.3,
    "前年同日比(移動平均14日)":3.6,
    "前年同日比(移動平均30日)":4.4
  },
  {
    "品目コード":"38400",
    "品目名":"えのきだけ",
    "日付":"2026-06-19",
    "価格":291.0,
    "平均":272.0,
    "最大値":742.0,
    "最小値":67.0,
    "中央値":264.0,
    "標準偏差":82.2,
    "分散":6764.9,
    "近似曲線_値":341.288,
    "移動平均_7日":288.6,
    "移動平均_14日":290.8,
    "移動平均_30日":297.8,
    "平均(同日)":235.5,
    "中央値(同日)":222.0,
    "比率-(移動平均7日\/近似曲線_値)":-15.4,
    "比率-(移動平均7日\/中央値)":9.3,
    "前年同日比(移動平均7日)":9.7,
    "前年同日比(移動平均14日)":11.4,
    "前年同日比(移動平均30日)":11.8
  },
  {
    "品目コード":"38500",
    "品目名":"しめじ",
    "日付":"2026-06-19",
    "価格":446.0,
    "平均":449.3,
    "最大値":877.0,
    "最小値":213.0,
    "中央値":445.0,
    "標準偏差":95.9,
    "分散":9197.4,
    "近似曲線_値":485.525,
    "移動平均_7日":441.9,
    "移動平均_14日":441.0,
    "移動平均_30日":451.5,
    "平均(同日)":382.6,
    "中央値(同日)":366.0,
    "比率-(移動平均7日\/近似曲線_値)":-9.0,
    "比率-(移動平均7日\/中央値)":-0.7,
    "前年同日比(移動平均7日)":2.0,
    "前年同日比(移動平均14日)":2.9,
    "前年同日比(移動平均30日)":4.2
  },
  {
    "品目コード":"39000",
    "品目名":"その他の野菜",
    "日付":"2026-06-19",
    "価格":913.0,
    "平均":839.9,
    "最大値":1658.0,
    "最小値":177.0,
    "中央値":830.0,
    "標準偏差":163.6,
    "分散":26778.7,
    "近似曲線_値":961.422,
    "移動平均_7日":897.7,
    "移動平均_14日":897.5,
    "移動平均_30日":895.3,
    "平均(同日)":742.4,
    "中央値(同日)":701.0,
    "比率-(移動平均7日\/近似曲線_値)":-6.6,
    "比率-(移動平均7日\/中央値)":8.2,
    "前年同日比(移動平均7日)":7.7,
    "前年同日比(移動平均14日)":7.5,
    "前年同日比(移動平均30日)":5.7
  }
]