[{"品目名":"きゅうり","品目コード":"06","調査期間_西暦":"2010-04-12","価格":519.0,"reg1":483.129},{"品目名":"きゅうり","品目コード":"06","調査期間_西暦":"2010-04-19","価格":543.0,"reg1":483.341},{"品目名":"きゅうり","品目コード":"06","調査期間_西暦":"2010-04-26","価格":564.0,"reg1":483.552},{"品目名":"きゅうり","品目コード":"06","調査期間_西暦":"2010-05-03","価格":497.0,"reg1":483.764},{"品目名":"きゅうり","品目コード":"06","調査期間_西暦":"2010-05-10","価格":416.0,"reg1":483.975},{"品目名":"きゅうり","品目コード":"06","調査期間_西暦":"2010-05-17","価格":393.0,"reg1":484.186},{"品目名":"きゅうり","品目コード":"06","調査期間_西暦":"2010-05-24","価格":390.0,"reg1":484.398},{"品目名":"きゅうり","品目コード":"06","調査期間_西暦":"2010-05-31","価格":429.0,"reg1":484.609},{"品目名":"きゅうり","品目コード":"06","調査期間_西暦":"2010-06-07","価格":461.0,"reg1":484.821},{"品目名":"きゅうり","品目コード":"06","調査期間_西暦":"2010-06-14","価格":409.0,"reg1":485.032},{"品目名":"きゅうり","品目コード":"06","調査期間_西暦":"2010-06-21","価格":376.0,"reg1":485.244},{"品目名":"きゅうり","品目コード":"06","調査期間_西暦":"2010-06-28","価格":421.0,"reg1":485.455},{"品目名":"きゅうり","品目コード":"06","調査期間_西暦":"2010-07-05","価格":425.0,"reg1":485.667},{"品目名":"きゅうり","品目コード":"06","調査期間_西暦":"2010-07-12","価格":454.0,"reg1":485.878},{"品目名":"きゅうり","品目コード":"06","調査期間_西暦":"2010-07-19","価格":453.0,"reg1":486.089},{"品目名":"きゅうり","品目コード":"06","調査期間_西暦":"2010-07-26","価格":416.0,"reg1":486.301},{"品目名":"きゅうり","品目コード":"06","調査期間_西暦":"2010-08-02","価格":407.0,"reg1":486.512},{"品目名":"きゅうり","品目コード":"06","調査期間_西暦":"2010-08-09","価格":395.0,"reg1":486.724},{"品目名":"きゅうり","品目コード":"06","調査期間_西暦":"2010-08-16","価格":438.0,"reg1":486.935},{"品目名":"きゅうり","品目コード":"06","調査期間_西暦":"2010-08-23","価格":517.0,"reg1":487.147},{"品目名":"きゅうり","品目コード":"06","調査期間_西暦":"2010-08-30","価格":506.0,"reg1":487.358},{"品目名":"きゅうり","品目コード":"06","調査期間_西暦":"2010-09-06","価格":504.0,"reg1":487.569},{"品目名":"きゅうり","品目コード":"06","調査期間_西暦":"2010-09-13","価格":521.0,"reg1":487.781},{"品目名":"きゅうり","品目コード":"06","調査期間_西暦":"2010-09-20","価格":557.0,"reg1":487.992},{"品目名":"きゅうり","品目コード":"06","調査期間_西暦":"2010-09-27","価格":537.0,"reg1":488.204},{"品目名":"きゅうり","品目コード":"06","調査期間_西暦":"2010-10-04","価格":575.0,"reg1":488.415},{"品目名":"きゅうり","品目コード":"06","調査期間_西暦":"2010-10-11","価格":562.0,"reg1":488.627},{"品目名":"きゅうり","品目コード":"06","調査期間_西暦":"2010-10-18","価格":507.0,"reg1":488.838},{"品目名":"きゅうり","品目コード":"06","調査期間_西暦":"2010-10-25","価格":507.0,"reg1":489.05},{"品目名":"きゅうり","品目コード":"06","調査期間_西暦":"2010-11-01","価格":591.0,"reg1":489.261},{"品目名":"きゅうり","品目コード":"06","調査期間_西暦":"2010-11-08","価格":739.0,"reg1":489.472},{"品目名":"きゅうり","品目コード":"06","調査期間_西暦":"2010-11-15","価格":654.0,"reg1":489.684},{"品目名":"きゅうり","品目コード":"06","調査期間_西暦":"2010-11-22","価格":574.0,"reg1":489.895},{"品目名":"きゅうり","品目コード":"06","調査期間_西暦":"2010-11-29","価格":561.0,"reg1":490.107},{"品目名":"きゅうり","品目コード":"06","調査期間_西暦":"2010-12-06","価格":534.0,"reg1":490.318},{"品目名":"きゅうり","品目コード":"06","調査期間_西暦":"2010-12-13","価格":515.0,"reg1":490.53},{"品目名":"きゅうり","品目コード":"06","調査期間_西暦":"2010-12-20","価格":549.0,"reg1":490.741},{"品目名":"きゅうり","品目コード":"06","調査期間_西暦":"2011-01-03","価格":673.0,"reg1":490.953},{"品目名":"きゅうり","品目コード":"06","調査期間_西暦":"2011-01-10","価格":610.0,"reg1":491.164},{"品目名":"きゅうり","品目コード":"06","調査期間_西暦":"2011-01-17","価格":null,"reg1":null},{"品目名":"きゅうり","品目コード":"06","調査期間_西暦":"2011-01-24","価格":null,"reg1":null},{"品目名":"きゅうり","品目コード":"06","調査期間_西暦":"2011-01-31","価格":null,"reg1":null},{"品目名":"きゅうり","品目コード":"06","調査期間_西暦":"2011-02-07","価格":null,"reg1":null},{"品目名":"きゅうり","品目コード":"06","調査期間_西暦":"2011-02-14","価格":null,"reg1":null},{"品目名":"きゅうり","品目コード":"06","調査期間_西暦":"2011-02-21","価格":null,"reg1":null},{"品目名":"きゅうり","品目コード":"06","調査期間_西暦":"2011-02-28","価格":null,"reg1":null},{"品目名":"きゅうり","品目コード":"06","調査期間_西暦":"2011-03-07","価格":null,"reg1":null},{"品目名":"きゅうり","品目コード":"06","調査期間_西暦":"2011-03-14","価格":null,"reg1":null},{"品目名":"きゅうり","品目コード":"06","調査期間_西暦":"2011-03-21","価格":null,"reg1":null},{"品目名":"きゅうり","品目コード":"06","調査期間_西暦":"2011-03-28","価格":null,"reg1":null},{"品目名":"きゅうり","品目コード":"06","調査期間_西暦":"2011-04-04","価格":null,"reg1":null},{"品目名":"きゅうり","品目コード":"06","調査期間_西暦":"2011-04-11","価格":null,"reg1":null},{"品目名":"きゅうり","品目コード":"06","調査期間_西暦":"2011-04-18","価格":null,"reg1":null},{"品目名":"きゅうり","品目コード":"06","調査期間_西暦":"2011-04-25","価格":null,"reg1":null},{"品目名":"きゅうり","品目コード":"06","調査期間_西暦":"2011-05-09","価格":null,"reg1":null},{"品目名":"きゅうり","品目コード":"06","調査期間_西暦":"2011-05-16","価格":null,"reg1":null},{"品目名":"きゅうり","品目コード":"06","調査期間_西暦":"2011-05-23","価格":null,"reg1":null},{"品目名":"きゅうり","品目コード":"06","調査期間_西暦":"2011-05-30","価格":null,"reg1":null},{"品目名":"きゅうり","品目コード":"06","調査期間_西暦":"2011-06-06","価格":null,"reg1":null},{"品目名":"きゅうり","品目コード":"06","調査期間_西暦":"2011-06-13","価格":null,"reg1":null},{"品目名":"きゅうり","品目コード":"06","調査期間_西暦":"2011-06-20","価格":null,"reg1":null},{"品目名":"きゅうり","品目コード":"06","調査期間_西暦":"2011-06-27","価格":null,"reg1":null},{"品目名":"きゅうり","品目コード":"06","調査期間_西暦":"2011-07-04","価格":null,"reg1":null},{"品目名":"きゅうり","品目コード":"06","調査期間_西暦":"2011-07-11","価格":null,"reg1":null},{"品目名":"きゅうり","品目コード":"06","調査期間_西暦":"2011-07-18","価格":null,"reg1":null},{"品目名":"きゅうり","品目コード":"06","調査期間_西暦":"2011-07-25","価格":null,"reg1":null},{"品目名":"きゅうり","品目コード":"06","調査期間_西暦":"2011-08-01","価格":null,"reg1":null},{"品目名":"きゅうり","品目コード":"06","調査期間_西暦":"2011-08-08","価格":null,"reg1":null},{"品目名":"きゅうり","品目コード":"06","調査期間_西暦":"2011-08-15","価格":null,"reg1":null},{"品目名":"きゅうり","品目コード":"06","調査期間_西暦":"2011-08-22","価格":null,"reg1":null},{"品目名":"きゅうり","品目コード":"06","調査期間_西暦":"2011-09-05","価格":null,"reg1":null},{"品目名":"きゅうり","品目コード":"06","調査期間_西暦":"2011-09-12","価格":null,"reg1":null},{"品目名":"きゅうり","品目コード":"06","調査期間_西暦":"2011-09-19","価格":null,"reg1":null},{"品目名":"きゅうり","品目コード":"06","調査期間_西暦":"2011-09-26","価格":null,"reg1":null},{"品目名":"きゅうり","品目コード":"06","調査期間_西暦":"2011-10-03","価格":null,"reg1":null},{"品目名":"きゅうり","品目コード":"06","調査期間_西暦":"2011-10-10","価格":null,"reg1":null},{"品目名":"きゅうり","品目コード":"06","調査期間_西暦":"2011-10-17","価格":null,"reg1":null},{"品目名":"きゅうり","品目コード":"06","調査期間_西暦":"2011-10-24","価格":null,"reg1":null},{"品目名":"きゅうり","品目コード":"06","調査期間_西暦":"2011-10-31","価格":null,"reg1":null},{"品目名":"きゅうり","品目コード":"06","調査期間_西暦":"2011-11-07","価格":null,"reg1":null},{"品目名":"きゅうり","品目コード":"06","調査期間_西暦":"2011-11-14","価格":null,"reg1":null},{"品目名":"きゅうり","品目コード":"06","調査期間_西暦":"2011-11-21","価格":null,"reg1":null},{"品目名":"きゅうり","品目コード":"06","調査期間_西暦":"2011-11-28","価格":null,"reg1":null},{"品目名":"きゅうり","品目コード":"06","調査期間_西暦":"2011-12-05","価格":null,"reg1":null},{"品目名":"きゅうり","品目コード":"06","調査期間_西暦":"2011-12-12","価格":null,"reg1":null},{"品目名":"きゅうり","品目コード":"06","調査期間_西暦":"2011-12-19","価格":null,"reg1":null},{"品目名":"きゅうり","品目コード":"06","調査期間_西暦":"2012-01-09","価格":null,"reg1":null},{"品目名":"きゅうり","品目コード":"06","調査期間_西暦":"2012-01-16","価格":null,"reg1":null},{"品目名":"きゅうり","品目コード":"06","調査期間_西暦":"2012-01-23","価格":null,"reg1":null},{"品目名":"きゅうり","品目コード":"06","調査期間_西暦":"2012-01-30","価格":null,"reg1":null},{"品目名":"きゅうり","品目コード":"06","調査期間_西暦":"2012-02-06","価格":null,"reg1":null},{"品目名":"きゅうり","品目コード":"06","調査期間_西暦":"2012-02-13","価格":null,"reg1":null},{"品目名":"きゅうり","品目コード":"06","調査期間_西暦":"2012-02-20","価格":null,"reg1":null},{"品目名":"きゅうり","品目コード":"06","調査期間_西暦":"2012-02-27","価格":null,"reg1":null},{"品目名":"きゅうり","品目コード":"06","調査期間_西暦":"2012-03-05","価格":null,"reg1":null},{"品目名":"きゅうり","品目コード":"06","調査期間_西暦":"2012-03-12","価格":null,"reg1":null},{"品目名":"きゅうり","品目コード":"06","調査期間_西暦":"2012-03-19","価格":null,"reg1":null},{"品目名":"きゅうり","品目コード":"06","調査期間_西暦":"2012-03-26","価格":null,"reg1":null},{"品目名":"きゅうり","品目コード":"06","調査期間_西暦":"2012-04-02","価格":null,"reg1":null},{"品目名":"きゅうり","品目コード":"06","調査期間_西暦":"2012-04-09","価格":null,"reg1":null},{"品目名":"きゅうり","品目コード":"06","調査期間_西暦":"2012-04-16","価格":null,"reg1":null},{"品目名":"きゅうり","品目コード":"06","調査期間_西暦":"2012-04-23","価格":null,"reg1":null},{"品目名":"きゅうり","品目コード":"06","調査期間_西暦":"2012-05-07","価格":451.0,"reg1":504.696},{"品目名":"きゅうり","品目コード":"06","調査期間_西暦":"2012-05-14","価格":448.0,"reg1":504.908},{"品目名":"きゅうり","品目コード":"06","調査期間_西暦":"2012-05-21","価格":451.0,"reg1":505.119},{"品目名":"きゅうり","品目コード":"06","調査期間_西暦":"2012-05-28","価格":434.0,"reg1":505.33},{"品目名":"きゅうり","品目コード":"06","調査期間_西暦":"2012-06-04","価格":402.0,"reg1":505.542},{"品目名":"きゅうり","品目コード":"06","調査期間_西暦":"2012-06-11","価格":377.0,"reg1":505.753},{"品目名":"きゅうり","品目コード":"06","調査期間_西暦":"2012-06-18","価格":376.0,"reg1":505.965},{"品目名":"きゅうり","品目コード":"06","調査期間_西暦":"2012-06-25","価格":410.0,"reg1":506.176},{"品目名":"きゅうり","品目コード":"06","調査期間_西暦":"2012-07-02","価格":460.0,"reg1":506.388},{"品目名":"きゅうり","品目コード":"06","調査期間_西暦":"2012-07-09","価格":445.0,"reg1":506.599},{"品目名":"きゅうり","品目コード":"06","調査期間_西暦":"2012-07-16","価格":422.0,"reg1":506.81},{"品目名":"きゅうり","品目コード":"06","調査期間_西暦":"2012-07-23","価格":427.0,"reg1":507.022},{"品目名":"きゅうり","品目コード":"06","調査期間_西暦":"2012-07-30","価格":424.0,"reg1":507.233},{"品目名":"きゅうり","品目コード":"06","調査期間_西暦":"2012-08-06","価格":408.0,"reg1":507.445},{"品目名":"きゅうり","品目コード":"06","調査期間_西暦":"2012-08-13","価格":426.0,"reg1":507.656},{"品目名":"きゅうり","品目コード":"06","調査期間_西暦":"2012-08-20","価格":426.0,"reg1":507.868},{"品目名":"きゅうり","品目コード":"06","調査期間_西暦":"2012-08-27","価格":437.0,"reg1":508.079},{"品目名":"きゅうり","品目コード":"06","調査期間_西暦":"2012-09-03","価格":431.0,"reg1":508.291},{"品目名":"きゅうり","品目コード":"06","調査期間_西暦":"2012-09-10","価格":421.0,"reg1":508.502},{"品目名":"きゅうり","品目コード":"06","調査期間_西暦":"2012-09-17","価格":406.0,"reg1":508.713},{"品目名":"きゅうり","品目コード":"06","調査期間_西暦":"2012-09-24","価格":415.0,"reg1":508.925},{"品目名":"きゅうり","品目コード":"06","調査期間_西暦":"2012-10-01","価格":482.0,"reg1":509.136},{"品目名":"きゅうり","品目コード":"06","調査期間_西暦":"2012-10-08","価格":null,"reg1":null},{"品目名":"きゅうり","品目コード":"06","調査期間_西暦":"2012-10-15","価格":null,"reg1":null},{"品目名":"きゅうり","品目コード":"06","調査期間_西暦":"2012-10-22","価格":null,"reg1":null},{"品目名":"きゅうり","品目コード":"06","調査期間_西暦":"2012-10-29","価格":null,"reg1":null},{"品目名":"きゅうり","品目コード":"06","調査期間_西暦":"2012-11-05","価格":null,"reg1":null},{"品目名":"きゅうり","品目コード":"06","調査期間_西暦":"2012-11-12","価格":null,"reg1":null},{"品目名":"きゅうり","品目コード":"06","調査期間_西暦":"2012-11-19","価格":null,"reg1":null},{"品目名":"きゅうり","品目コード":"06","調査期間_西暦":"2012-11-26","価格":null,"reg1":null},{"品目名":"きゅうり","品目コード":"06","調査期間_西暦":"2012-12-03","価格":null,"reg1":null},{"品目名":"きゅうり","品目コード":"06","調査期間_西暦":"2012-12-10","価格":null,"reg1":null},{"品目名":"きゅうり","品目コード":"06","調査期間_西暦":"2012-12-17","価格":null,"reg1":null},{"品目名":"きゅうり","品目コード":"06","調査期間_西暦":"2012-12-24","価格":null,"reg1":null},{"品目名":"きゅうり","品目コード":"06","調査期間_西暦":"2013-01-07","価格":null,"reg1":null},{"品目名":"きゅうり","品目コード":"06","調査期間_西暦":"2013-01-14","価格":781.0,"reg1":512.096},{"品目名":"きゅうり","品目コード":"06","調査期間_西暦":"2013-01-21","価格":753.0,"reg1":512.308},{"品目名":"きゅうり","品目コード":"06","調査期間_西暦":"2013-01-28","価格":700.0,"reg1":512.519},{"品目名":"きゅうり","品目コード":"06","調査期間_西暦":"2013-02-04","価格":652.0,"reg1":512.731},{"品目名":"きゅうり","品目コード":"06","調査期間_西暦":"2013-02-11","価格":565.0,"reg1":512.942},{"品目名":"きゅうり","品目コード":"06","調査期間_西暦":"2013-02-18","価格":530.0,"reg1":513.154},{"品目名":"きゅうり","品目コード":"06","調査期間_西暦":"2013-02-25","価格":547.0,"reg1":513.365},{"品目名":"きゅうり","品目コード":"06","調査期間_西暦":"2013-03-04","価格":534.0,"reg1":513.577},{"品目名":"きゅうり","品目コード":"06","調査期間_西暦":"2013-03-11","価格":494.0,"reg1":513.788},{"品目名":"きゅうり","品目コード":"06","調査期間_西暦":"2013-03-18","価格":457.0,"reg1":513.999},{"品目名":"きゅうり","品目コード":"06","調査期間_西暦":"2013-03-25","価格":427.0,"reg1":514.211},{"品目名":"きゅうり","品目コード":"06","調査期間_西暦":"2013-04-01","価格":null,"reg1":null},{"品目名":"きゅうり","品目コード":"06","調査期間_西暦":"2013-04-08","価格":null,"reg1":null},{"品目名":"きゅうり","品目コード":"06","調査期間_西暦":"2013-04-15","価格":null,"reg1":null},{"品目名":"きゅうり","品目コード":"06","調査期間_西暦":"2013-04-22","価格":null,"reg1":null},{"品目名":"きゅうり","品目コード":"06","調査期間_西暦":"2013-04-29","価格":null,"reg1":null},{"品目名":"きゅうり","品目コード":"06","調査期間_西暦":"2013-05-06","価格":null,"reg1":null},{"品目名":"きゅうり","品目コード":"06","調査期間_西暦":"2013-05-13","価格":null,"reg1":null},{"品目名":"きゅうり","品目コード":"06","調査期間_西暦":"2013-05-20","価格":null,"reg1":null},{"品目名":"きゅうり","品目コード":"06","調査期間_西暦":"2013-05-27","価格":null,"reg1":null},{"品目名":"きゅうり","品目コード":"06","調査期間_西暦":"2013-06-03","価格":null,"reg1":null},{"品目名":"きゅうり","品目コード":"06","調査期間_西暦":"2013-06-10","価格":null,"reg1":null},{"品目名":"きゅうり","品目コード":"06","調査期間_西暦":"2013-06-17","価格":null,"reg1":null},{"品目名":"きゅうり","品目コード":"06","調査期間_西暦":"2013-06-24","価格":null,"reg1":null},{"品目名":"きゅうり","品目コード":"06","調査期間_西暦":"2013-07-01","価格":null,"reg1":null},{"品目名":"きゅうり","品目コード":"06","調査期間_西暦":"2013-07-08","価格":null,"reg1":null},{"品目名":"きゅうり","品目コード":"06","調査期間_西暦":"2013-07-15","価格":null,"reg1":null},{"品目名":"きゅうり","品目コード":"06","調査期間_西暦":"2013-07-22","価格":447.0,"reg1":517.805},{"品目名":"きゅうり","品目コード":"06","調査期間_西暦":"2013-07-29","価格":460.0,"reg1":518.017},{"品目名":"きゅうり","品目コード":"06","調査期間_西暦":"2013-08-05","価格":457.0,"reg1":518.228},{"品目名":"きゅうり","品目コード":"06","調査期間_西暦":"2013-08-12","価格":466.0,"reg1":518.44},{"品目名":"きゅうり","品目コード":"06","調査期間_西暦":"2013-08-19","価格":453.0,"reg1":518.651},{"品目名":"きゅうり","品目コード":"06","調査期間_西暦":"2013-08-26","価格":521.0,"reg1":518.863},{"品目名":"きゅうり","品目コード":"06","調査期間_西暦":"2013-09-02","価格":621.0,"reg1":519.074},{"品目名":"きゅうり","品目コード":"06","調査期間_西暦":"2013-09-09","価格":670.0,"reg1":519.285},{"品目名":"きゅうり","品目コード":"06","調査期間_西暦":"2013-09-16","価格":690.0,"reg1":519.497},{"品目名":"きゅうり","品目コード":"06","調査期間_西暦":"2013-09-23","価格":650.0,"reg1":519.708},{"品目名":"きゅうり","品目コード":"06","調査期間_西暦":"2013-09-30","価格":613.0,"reg1":519.92},{"品目名":"きゅうり","品目コード":"06","調査期間_西暦":"2013-10-07","価格":null,"reg1":null},{"品目名":"きゅうり","品目コード":"06","調査期間_西暦":"2013-10-14","価格":null,"reg1":null},{"品目名":"きゅうり","品目コード":"06","調査期間_西暦":"2013-10-21","価格":null,"reg1":null},{"品目名":"きゅうり","品目コード":"06","調査期間_西暦":"2013-10-28","価格":null,"reg1":null},{"品目名":"きゅうり","品目コード":"06","調査期間_西暦":"2013-11-04","価格":null,"reg1":null},{"品目名":"きゅうり","品目コード":"06","調査期間_西暦":"2013-11-11","価格":null,"reg1":null},{"品目名":"きゅうり","品目コード":"06","調査期間_西暦":"2013-11-18","価格":null,"reg1":null},{"品目名":"きゅうり","品目コード":"06","調査期間_西暦":"2013-11-25","価格":null,"reg1":null},{"品目名":"きゅうり","品目コード":"06","調査期間_西暦":"2013-12-02","価格":null,"reg1":null},{"品目名":"きゅうり","品目コード":"06","調査期間_西暦":"2013-12-09","価格":null,"reg1":null},{"品目名":"きゅうり","品目コード":"06","調査期間_西暦":"2013-12-16","価格":null,"reg1":null},{"品目名":"きゅうり","品目コード":"06","調査期間_西暦":"2013-12-23","価格":null,"reg1":null},{"品目名":"きゅうり","品目コード":"06","調査期間_西暦":"2014-01-06","価格":null,"reg1":null},{"品目名":"きゅうり","品目コード":"06","調査期間_西暦":"2014-01-13","価格":null,"reg1":null},{"品目名":"きゅうり","品目コード":"06","調査期間_西暦":"2014-01-20","価格":null,"reg1":null},{"品目名":"きゅうり","品目コード":"06","調査期間_西暦":"2014-01-27","価格":null,"reg1":null},{"品目名":"きゅうり","品目コード":"06","調査期間_西暦":"2014-02-03","価格":null,"reg1":null},{"品目名":"きゅうり","品目コード":"06","調査期間_西暦":"2014-02-10","価格":null,"reg1":null},{"品目名":"きゅうり","品目コード":"06","調査期間_西暦":"2014-02-17","価格":null,"reg1":null},{"品目名":"きゅうり","品目コード":"06","調査期間_西暦":"2014-02-24","価格":null,"reg1":null},{"品目名":"きゅうり","品目コード":"06","調査期間_西暦":"2014-03-03","価格":null,"reg1":null},{"品目名":"きゅうり","品目コード":"06","調査期間_西暦":"2014-03-10","価格":null,"reg1":null},{"品目名":"きゅうり","品目コード":"06","調査期間_西暦":"2014-03-17","価格":null,"reg1":null},{"品目名":"きゅうり","品目コード":"06","調査期間_西暦":"2014-03-24","価格":null,"reg1":null},{"品目名":"きゅうり","品目コード":"06","調査期間_西暦":"2014-03-31","価格":514.0,"reg1":525.206},{"品目名":"きゅうり","品目コード":"06","調査期間_西暦":"2014-04-07","価格":499.0,"reg1":525.417},{"品目名":"きゅうり","品目コード":"06","調査期間_西暦":"2014-04-14","価格":506.0,"reg1":525.629},{"品目名":"きゅうり","品目コード":"06","調査期間_西暦":"2014-04-21","価格":492.0,"reg1":525.84},{"品目名":"きゅうり","品目コード":"06","調査期間_西暦":"2014-04-28","価格":495.0,"reg1":526.052},{"品目名":"きゅうり","品目コード":"06","調査期間_西暦":"2014-05-05","価格":490.0,"reg1":526.263},{"品目名":"きゅうり","品目コード":"06","調査期間_西暦":"2014-05-12","価格":483.0,"reg1":526.474},{"品目名":"きゅうり","品目コード":"06","調査期間_西暦":"2014-05-19","価格":475.0,"reg1":526.686},{"品目名":"きゅうり","品目コード":"06","調査期間_西暦":"2014-05-26","価格":462.0,"reg1":526.897},{"品目名":"きゅうり","品目コード":"06","調査期間_西暦":"2014-06-02","価格":447.0,"reg1":527.109},{"品目名":"きゅうり","品目コード":"06","調査期間_西暦":"2014-06-09","価格":431.0,"reg1":527.32},{"品目名":"きゅうり","品目コード":"06","調査期間_西暦":"2014-06-16","価格":443.0,"reg1":527.532},{"品目名":"きゅうり","品目コード":"06","調査期間_西暦":"2014-06-23","価格":496.0,"reg1":527.743},{"品目名":"きゅうり","品目コード":"06","調査期間_西暦":"2014-06-30","価格":479.0,"reg1":527.954},{"品目名":"きゅうり","品目コード":"06","調査期間_西暦":"2014-07-07","価格":443.0,"reg1":528.166},{"品目名":"きゅうり","品目コード":"06","調査期間_西暦":"2014-07-14","価格":437.0,"reg1":528.377},{"品目名":"きゅうり","品目コード":"06","調査期間_西暦":"2014-07-21","価格":437.0,"reg1":528.589},{"品目名":"きゅうり","品目コード":"06","調査期間_西暦":"2014-07-28","価格":437.0,"reg1":528.8},{"品目名":"きゅうり","品目コード":"06","調査期間_西暦":"2014-08-04","価格":428.0,"reg1":529.012},{"品目名":"きゅうり","品目コード":"06","調査期間_西暦":"2014-08-11","価格":517.0,"reg1":529.223},{"品目名":"きゅうり","品目コード":"06","調査期間_西暦":"2014-08-18","価格":785.0,"reg1":529.435},{"品目名":"きゅうり","品目コード":"06","調査期間_西暦":"2014-08-25","価格":823.0,"reg1":529.646},{"品目名":"きゅうり","品目コード":"06","調査期間_西暦":"2014-09-01","価格":826.0,"reg1":529.857},{"品目名":"きゅうり","品目コード":"06","調査期間_西暦":"2014-09-08","価格":761.0,"reg1":530.069},{"品目名":"きゅうり","品目コード":"06","調査期間_西暦":"2014-09-15","価格":661.0,"reg1":530.28},{"品目名":"きゅうり","品目コード":"06","調査期間_西暦":"2014-09-22","価格":612.0,"reg1":530.492},{"品目名":"きゅうり","品目コード":"06","調査期間_西暦":"2014-09-29","価格":588.0,"reg1":530.703},{"品目名":"きゅうり","品目コード":"06","調査期間_西暦":"2014-10-06","価格":517.0,"reg1":530.915},{"品目名":"きゅうり","品目コード":"06","調査期間_西暦":"2014-10-13","価格":500.0,"reg1":531.126},{"品目名":"きゅうり","品目コード":"06","調査期間_西暦":"2014-10-20","価格":539.0,"reg1":531.338},{"品目名":"きゅうり","品目コード":"06","調査期間_西暦":"2014-10-27","価格":561.0,"reg1":531.549},{"品目名":"きゅうり","品目コード":"06","調査期間_西暦":"2014-11-03","価格":null,"reg1":null},{"品目名":"きゅうり","品目コード":"06","調査期間_西暦":"2014-11-10","価格":null,"reg1":null},{"品目名":"きゅうり","品目コード":"06","調査期間_西暦":"2014-11-17","価格":null,"reg1":null},{"品目名":"きゅうり","品目コード":"06","調査期間_西暦":"2014-11-24","価格":null,"reg1":null},{"品目名":"きゅうり","品目コード":"06","調査期間_西暦":"2014-12-01","価格":null,"reg1":null},{"品目名":"きゅうり","品目コード":"06","調査期間_西暦":"2014-12-08","価格":null,"reg1":null},{"品目名":"きゅうり","品目コード":"06","調査期間_西暦":"2014-12-15","価格":null,"reg1":null},{"品目名":"きゅうり","品目コード":"06","調査期間_西暦":"2014-12-22","価格":null,"reg1":null},{"品目名":"きゅうり","品目コード":"06","調査期間_西暦":"2015-01-05","価格":null,"reg1":null},{"品目名":"きゅうり","品目コード":"06","調査期間_西暦":"2015-01-12","価格":null,"reg1":null},{"品目名":"きゅうり","品目コード":"06","調査期間_西暦":"2015-01-19","価格":null,"reg1":null},{"品目名":"きゅうり","品目コード":"06","調査期間_西暦":"2015-01-26","価格":null,"reg1":null},{"品目名":"きゅうり","品目コード":"06","調査期間_西暦":"2015-02-02","価格":null,"reg1":null},{"品目名":"きゅうり","品目コード":"06","調査期間_西暦":"2015-02-09","価格":null,"reg1":null},{"品目名":"きゅうり","品目コード":"06","調査期間_西暦":"2015-02-16","価格":null,"reg1":null},{"品目名":"きゅうり","品目コード":"06","調査期間_西暦":"2015-02-23","価格":null,"reg1":null},{"品目名":"きゅうり","品目コード":"06","調査期間_西暦":"2015-03-02","価格":null,"reg1":null},{"品目名":"きゅうり","品目コード":"06","調査期間_西暦":"2015-03-09","価格":null,"reg1":null},{"品目名":"きゅうり","品目コード":"06","調査期間_西暦":"2015-03-16","価格":null,"reg1":null},{"品目名":"きゅうり","品目コード":"06","調査期間_西暦":"2015-03-23","価格":null,"reg1":null},{"品目名":"きゅうり","品目コード":"06","調査期間_西暦":"2015-03-30","価格":597.0,"reg1":535.989},{"品目名":"きゅうり","品目コード":"06","調査期間_西暦":"2015-04-06","価格":562.0,"reg1":536.201},{"品目名":"きゅうり","品目コード":"06","調査期間_西暦":"2015-04-13","価格":635.0,"reg1":536.412},{"品目名":"きゅうり","品目コード":"06","調査期間_西暦":"2015-04-20","価格":770.0,"reg1":536.623},{"品目名":"きゅうり","品目コード":"06","調査期間_西暦":"2015-04-27","価格":671.0,"reg1":536.835},{"品目名":"きゅうり","品目コード":"06","調査期間_西暦":"2015-05-11","価格":523.0,"reg1":537.046},{"品目名":"きゅうり","品目コード":"06","調査期間_西暦":"2015-05-18","価格":522.0,"reg1":537.258},{"品目名":"きゅうり","品目コード":"06","調査期間_西暦":"2015-05-25","価格":505.0,"reg1":537.469},{"品目名":"きゅうり","品目コード":"06","調査期間_西暦":"2015-06-01","価格":472.0,"reg1":537.681},{"品目名":"きゅうり","品目コード":"06","調査期間_西暦":"2015-06-08","価格":454.0,"reg1":537.892},{"品目名":"きゅうり","品目コード":"06","調査期間_西暦":"2015-06-15","価格":491.0,"reg1":538.104},{"品目名":"きゅうり","品目コード":"06","調査期間_西暦":"2015-06-22","価格":499.0,"reg1":538.315},{"品目名":"きゅうり","品目コード":"06","調査期間_西暦":"2015-06-29","価格":490.0,"reg1":538.526},{"品目名":"きゅうり","品目コード":"06","調査期間_西暦":"2015-07-06","価格":483.0,"reg1":538.738},{"品目名":"きゅうり","品目コード":"06","調査期間_西暦":"2015-07-13","価格":519.0,"reg1":538.949},{"品目名":"きゅうり","品目コード":"06","調査期間_西暦":"2015-07-20","価格":518.0,"reg1":539.161},{"品目名":"きゅうり","品目コード":"06","調査期間_西暦":"2015-07-27","価格":525.0,"reg1":539.372},{"品目名":"きゅうり","品目コード":"06","調査期間_西暦":"2015-08-03","価格":539.0,"reg1":539.584},{"品目名":"きゅうり","品目コード":"06","調査期間_西暦":"2015-08-10","価格":554.0,"reg1":539.795},{"品目名":"きゅうり","品目コード":"06","調査期間_西暦":"2015-08-17","価格":562.0,"reg1":540.007},{"品目名":"きゅうり","品目コード":"06","調査期間_西暦":"2015-08-24","価格":558.0,"reg1":540.218},{"品目名":"きゅうり","品目コード":"06","調査期間_西暦":"2015-08-31","価格":638.0,"reg1":540.429},{"品目名":"きゅうり","品目コード":"06","調査期間_西暦":"2015-09-07","価格":736.0,"reg1":540.641},{"品目名":"きゅうり","品目コード":"06","調査期間_西暦":"2015-09-14","価格":763.0,"reg1":540.852},{"品目名":"きゅうり","品目コード":"06","調査期間_西暦":"2015-09-28","価格":661.0,"reg1":541.064},{"品目名":"きゅうり","品目コード":"06","調査期間_西暦":"2015-10-05","価格":null,"reg1":null},{"品目名":"きゅうり","品目コード":"06","調査期間_西暦":"2015-10-12","価格":null,"reg1":null},{"品目名":"きゅうり","品目コード":"06","調査期間_西暦":"2015-10-19","価格":null,"reg1":null},{"品目名":"きゅうり","品目コード":"06","調査期間_西暦":"2015-10-26","価格":null,"reg1":null},{"品目名":"きゅうり","品目コード":"06","調査期間_西暦":"2015-11-02","価格":null,"reg1":null},{"品目名":"きゅうり","品目コード":"06","調査期間_西暦":"2015-11-09","価格":null,"reg1":null},{"品目名":"きゅうり","品目コード":"06","調査期間_西暦":"2015-11-16","価格":null,"reg1":null},{"品目名":"きゅうり","品目コード":"06","調査期間_西暦":"2015-11-23","価格":null,"reg1":null},{"品目名":"きゅうり","品目コード":"06","調査期間_西暦":"2015-11-30","価格":null,"reg1":null},{"品目名":"きゅうり","品目コード":"06","調査期間_西暦":"2015-12-07","価格":null,"reg1":null},{"品目名":"きゅうり","品目コード":"06","調査期間_西暦":"2015-12-14","価格":null,"reg1":null},{"品目名":"きゅうり","品目コード":"06","調査期間_西暦":"2015-12-21","価格":null,"reg1":null},{"品目名":"きゅうり","品目コード":"06","調査期間_西暦":"2016-01-04","価格":null,"reg1":null},{"品目名":"きゅうり","品目コード":"06","調査期間_西暦":"2016-01-11","価格":null,"reg1":null},{"品目名":"きゅうり","品目コード":"06","調査期間_西暦":"2016-01-18","価格":null,"reg1":null},{"品目名":"きゅうり","品目コード":"06","調査期間_西暦":"2016-01-25","価格":null,"reg1":null},{"品目名":"きゅうり","品目コード":"06","調査期間_西暦":"2016-02-01","価格":null,"reg1":null},{"品目名":"きゅうり","品目コード":"06","調査期間_西暦":"2016-02-08","価格":null,"reg1":null},{"品目名":"きゅうり","品目コード":"06","調査期間_西暦":"2016-02-15","価格":null,"reg1":null},{"品目名":"きゅうり","品目コード":"06","調査期間_西暦":"2016-02-22","価格":null,"reg1":null},{"品目名":"きゅうり","品目コード":"06","調査期間_西暦":"2016-02-29","価格":null,"reg1":null},{"品目名":"きゅうり","品目コード":"06","調査期間_西暦":"2016-03-07","価格":null,"reg1":null},{"品目名":"きゅうり","品目コード":"06","調査期間_西暦":"2016-03-14","価格":null,"reg1":null},{"品目名":"きゅうり","品目コード":"06","調査期間_西暦":"2016-03-21","価格":null,"reg1":null},{"品目名":"きゅうり","品目コード":"06","調査期間_西暦":"2016-03-28","価格":null,"reg1":null},{"品目名":"きゅうり","品目コード":"06","調査期間_西暦":"2016-04-04","価格":540.0,"reg1":546.561},{"品目名":"きゅうり","品目コード":"06","調査期間_西暦":"2016-04-11","価格":518.0,"reg1":546.773},{"品目名":"きゅうり","品目コード":"06","調査期間_西暦":"2016-04-18","価格":530.0,"reg1":546.984},{"品目名":"きゅうり","品目コード":"06","調査期間_西暦":"2016-04-25","価格":528.0,"reg1":547.195},{"品目名":"きゅうり","品目コード":"06","調査期間_西暦":"2016-05-09","価格":511.0,"reg1":547.407},{"品目名":"きゅうり","品目コード":"06","調査期間_西暦":"2016-05-16","価格":490.0,"reg1":547.618},{"品目名":"きゅうり","品目コード":"06","調査期間_西暦":"2016-05-23","価格":501.0,"reg1":547.83},{"品目名":"きゅうり","品目コード":"06","調査期間_西暦":"2016-05-30","価格":486.0,"reg1":548.041},{"品目名":"きゅうり","品目コード":"06","調査期間_西暦":"2016-06-06","価格":492.0,"reg1":548.253},{"品目名":"きゅうり","品目コード":"06","調査期間_西暦":"2016-06-13","価格":514.0,"reg1":548.464},{"品目名":"きゅうり","品目コード":"06","調査期間_西暦":"2016-06-20","価格":490.0,"reg1":548.676},{"品目名":"きゅうり","品目コード":"06","調査期間_西暦":"2016-06-27","価格":490.0,"reg1":548.887},{"品目名":"きゅうり","品目コード":"06","調査期間_西暦":"2016-07-04","価格":542.0,"reg1":549.098},{"品目名":"きゅうり","品目コード":"06","調査期間_西暦":"2016-07-11","価格":570.0,"reg1":549.31},{"品目名":"きゅうり","品目コード":"06","調査期間_西暦":"2016-07-18","価格":582.0,"reg1":549.521},{"品目名":"きゅうり","品目コード":"06","調査期間_西暦":"2016-07-25","価格":556.0,"reg1":549.733},{"品目名":"きゅうり","品目コード":"06","調査期間_西暦":"2016-08-01","価格":520.0,"reg1":549.944},{"品目名":"きゅうり","品目コード":"06","調査期間_西暦":"2016-08-08","価格":485.0,"reg1":550.156},{"品目名":"きゅうり","品目コード":"06","調査期間_西暦":"2016-08-15","価格":497.0,"reg1":550.367},{"品目名":"きゅうり","品目コード":"06","調査期間_西暦":"2016-08-22","価格":510.0,"reg1":550.579},{"品目名":"きゅうり","品目コード":"06","調査期間_西暦":"2016-08-29","価格":537.0,"reg1":550.79},{"品目名":"きゅうり","品目コード":"06","調査期間_西暦":"2016-09-05","価格":604.0,"reg1":551.001},{"品目名":"きゅうり","品目コード":"06","調査期間_西暦":"2016-09-12","価格":597.0,"reg1":551.213},{"品目名":"きゅうり","品目コード":"06","調査期間_西暦":"2016-09-19","価格":588.0,"reg1":551.424},{"品目名":"きゅうり","品目コード":"06","調査期間_西暦":"2016-09-26","価格":628.0,"reg1":551.636},{"品目名":"きゅうり","品目コード":"06","調査期間_西暦":"2016-10-03","価格":663.0,"reg1":551.847},{"品目名":"きゅうり","品目コード":"06","調査期間_西暦":"2016-10-10","価格":705.0,"reg1":552.059},{"品目名":"きゅうり","品目コード":"06","調査期間_西暦":"2016-10-17","価格":850.0,"reg1":552.27},{"品目名":"きゅうり","品目コード":"06","調査期間_西暦":"2016-10-24","価格":895.0,"reg1":552.481},{"品目名":"きゅうり","品目コード":"06","調査期間_西暦":"2016-10-31","価格":866.0,"reg1":552.693},{"品目名":"きゅうり","品目コード":"06","調査期間_西暦":"2016-11-07","価格":null,"reg1":null},{"品目名":"きゅうり","品目コード":"06","調査期間_西暦":"2016-11-14","価格":null,"reg1":null},{"品目名":"きゅうり","品目コード":"06","調査期間_西暦":"2016-11-21","価格":null,"reg1":null},{"品目名":"きゅうり","品目コード":"06","調査期間_西暦":"2016-11-28","価格":null,"reg1":null},{"品目名":"きゅうり","品目コード":"06","調査期間_西暦":"2016-12-05","価格":null,"reg1":null},{"品目名":"きゅうり","品目コード":"06","調査期間_西暦":"2016-12-12","価格":null,"reg1":null},{"品目名":"きゅうり","品目コード":"06","調査期間_西暦":"2016-12-19","価格":null,"reg1":null},{"品目名":"きゅうり","品目コード":"06","調査期間_西暦":"2016-12-26","価格":null,"reg1":null},{"品目名":"きゅうり","品目コード":"06","調査期間_西暦":"2017-01-09","価格":null,"reg1":null},{"品目名":"きゅうり","品目コード":"06","調査期間_西暦":"2017-01-16","価格":null,"reg1":null},{"品目名":"きゅうり","品目コード":"06","調査期間_西暦":"2017-01-23","価格":null,"reg1":null},{"品目名":"きゅうり","品目コード":"06","調査期間_西暦":"2017-01-30","価格":null,"reg1":null},{"品目名":"きゅうり","品目コード":"06","調査期間_西暦":"2017-02-06","価格":null,"reg1":null},{"品目名":"きゅうり","品目コード":"06","調査期間_西暦":"2017-02-13","価格":null,"reg1":null},{"品目名":"きゅうり","品目コード":"06","調査期間_西暦":"2017-02-20","価格":null,"reg1":null},{"品目名":"きゅうり","品目コード":"06","調査期間_西暦":"2017-02-27","価格":null,"reg1":null},{"品目名":"きゅうり","品目コード":"06","調査期間_西暦":"2017-03-06","価格":null,"reg1":null},{"品目名":"きゅうり","品目コード":"06","調査期間_西暦":"2017-03-13","価格":null,"reg1":null},{"品目名":"きゅうり","品目コード":"06","調査期間_西暦":"2017-03-20","価格":null,"reg1":null},{"品目名":"きゅうり","品目コード":"06","調査期間_西暦":"2017-03-27","価格":null,"reg1":null},{"品目名":"きゅうり","品目コード":"06","調査期間_西暦":"2017-04-03","価格":513.0,"reg1":557.133},{"品目名":"きゅうり","品目コード":"06","調査期間_西暦":"2017-04-10","価格":501.0,"reg1":557.345},{"品目名":"きゅうり","品目コード":"06","調査期間_西暦":"2017-04-17","価格":519.0,"reg1":557.556},{"品目名":"きゅうり","品目コード":"06","調査期間_西暦":"2017-04-24","価格":511.0,"reg1":557.767},{"品目名":"きゅうり","品目コード":"06","調査期間_西暦":"2017-05-08","価格":494.0,"reg1":557.979},{"品目名":"きゅうり","品目コード":"06","調査期間_西暦":"2017-05-15","価格":473.0,"reg1":558.19},{"品目名":"きゅうり","品目コード":"06","調査期間_西暦":"2017-05-22","価格":466.0,"reg1":558.402},{"品目名":"きゅうり","品目コード":"06","調査期間_西暦":"2017-05-29","価格":448.0,"reg1":558.613},{"品目名":"きゅうり","品目コード":"06","調査期間_西暦":"2017-06-05","価格":446.0,"reg1":558.825},{"品目名":"きゅうり","品目コード":"06","調査期間_西暦":"2017-06-12","価格":457.0,"reg1":559.036},{"品目名":"きゅうり","品目コード":"06","調査期間_西暦":"2017-06-19","価格":474.0,"reg1":559.248},{"品目名":"きゅうり","品目コード":"06","調査期間_西暦":"2017-06-26","価格":468.0,"reg1":559.459},{"品目名":"きゅうり","品目コード":"06","調査期間_西暦":"2017-07-03","価格":449.0,"reg1":559.67},{"品目名":"きゅうり","品目コード":"06","調査期間_西暦":"2017-07-10","価格":441.0,"reg1":559.882},{"品目名":"きゅうり","品目コード":"06","調査期間_西暦":"2017-07-17","価格":495.0,"reg1":560.093},{"品目名":"きゅうり","品目コード":"06","調査期間_西暦":"2017-07-24","価格":473.0,"reg1":560.305},{"品目名":"きゅうり","品目コード":"06","調査期間_西暦":"2017-07-31","価格":461.0,"reg1":560.516},{"品目名":"きゅうり","品目コード":"06","調査期間_西暦":"2017-08-07","価格":472.0,"reg1":560.728},{"品目名":"きゅうり","品目コード":"06","調査期間_西暦":"2017-08-14","価格":560.0,"reg1":560.939},{"品目名":"きゅうり","品目コード":"06","調査期間_西暦":"2017-08-21","価格":643.0,"reg1":561.151},{"品目名":"きゅうり","品目コード":"06","調査期間_西暦":"2017-08-28","価格":638.0,"reg1":561.362},{"品目名":"きゅうり","品目コード":"06","調査期間_西暦":"2017-09-04","価格":625.0,"reg1":561.573},{"品目名":"きゅうり","品目コード":"06","調査期間_西暦":"2017-09-11","価格":628.0,"reg1":561.785},{"品目名":"きゅうり","品目コード":"06","調査期間_西暦":"2017-09-18","価格":614.0,"reg1":561.996},{"品目名":"きゅうり","品目コード":"06","調査期間_西暦":"2017-09-25","価格":580.0,"reg1":562.208},{"品目名":"きゅうり","品目コード":"06","調査期間_西暦":"2017-10-02","価格":null,"reg1":null},{"品目名":"きゅうり","品目コード":"06","調査期間_西暦":"2017-10-09","価格":null,"reg1":null},{"品目名":"きゅうり","品目コード":"06","調査期間_西暦":"2017-10-16","価格":null,"reg1":null},{"品目名":"きゅうり","品目コード":"06","調査期間_西暦":"2017-10-23","価格":null,"reg1":null},{"品目名":"きゅうり","品目コード":"06","調査期間_西暦":"2017-10-30","価格":null,"reg1":null},{"品目名":"きゅうり","品目コード":"06","調査期間_西暦":"2017-11-06","価格":null,"reg1":null},{"品目名":"きゅうり","品目コード":"06","調査期間_西暦":"2017-11-13","価格":null,"reg1":null},{"品目名":"きゅうり","品目コード":"06","調査期間_西暦":"2017-11-20","価格":null,"reg1":null},{"品目名":"きゅうり","品目コード":"06","調査期間_西暦":"2017-11-27","価格":null,"reg1":null},{"品目名":"きゅうり","品目コード":"06","調査期間_西暦":"2017-12-04","価格":null,"reg1":null},{"品目名":"きゅうり","品目コード":"06","調査期間_西暦":"2017-12-11","価格":null,"reg1":null},{"品目名":"きゅうり","品目コード":"06","調査期間_西暦":"2017-12-18","価格":null,"reg1":null},{"品目名":"きゅうり","品目コード":"06","調査期間_西暦":"2017-12-25","価格":null,"reg1":null},{"品目名":"きゅうり","品目コード":"06","調査期間_西暦":"2018-01-08","価格":null,"reg1":null},{"品目名":"きゅうり","品目コード":"06","調査期間_西暦":"2018-01-15","価格":null,"reg1":null},{"品目名":"きゅうり","品目コード":"06","調査期間_西暦":"2018-01-22","価格":null,"reg1":null},{"品目名":"きゅうり","品目コード":"06","調査期間_西暦":"2018-01-29","価格":null,"reg1":null},{"品目名":"きゅうり","品目コード":"06","調査期間_西暦":"2018-02-05","価格":null,"reg1":null},{"品目名":"きゅうり","品目コード":"06","調査期間_西暦":"2018-02-12","価格":null,"reg1":null},{"品目名":"きゅうり","品目コード":"06","調査期間_西暦":"2018-02-19","価格":null,"reg1":null},{"品目名":"きゅうり","品目コード":"06","調査期間_西暦":"2018-02-26","価格":null,"reg1":null},{"品目名":"きゅうり","品目コード":"06","調査期間_西暦":"2018-03-05","価格":null,"reg1":null},{"品目名":"きゅうり","品目コード":"06","調査期間_西暦":"2018-03-12","価格":null,"reg1":null},{"品目名":"きゅうり","品目コード":"06","調査期間_西暦":"2018-03-19","価格":null,"reg1":null},{"品目名":"きゅうり","品目コード":"06","調査期間_西暦":"2018-03-26","価格":null,"reg1":null},{"品目名":"きゅうり","品目コード":"06","調査期間_西暦":"2018-04-02","価格":null,"reg1":null},{"品目名":"きゅうり","品目コード":"06","調査期間_西暦":"2018-04-09","価格":492.0,"reg1":567.917},{"品目名":"きゅうり","品目コード":"06","調査期間_西暦":"2018-04-16","価格":464.0,"reg1":568.128},{"品目名":"きゅうり","品目コード":"06","調査期間_西暦":"2018-04-23","価格":457.0,"reg1":568.339},{"品目名":"きゅうり","品目コード":"06","調査期間_西暦":"2018-05-07","価格":452.0,"reg1":568.551},{"品目名":"きゅうり","品目コード":"06","調査期間_西暦":"2018-05-14","価格":495.0,"reg1":568.762},{"品目名":"きゅうり","品目コード":"06","調査期間_西暦":"2018-05-21","価格":528.0,"reg1":568.974},{"品目名":"きゅうり","品目コード":"06","調査期間_西暦":"2018-05-28","価格":504.0,"reg1":569.185},{"品目名":"きゅうり","品目コード":"06","調査期間_西暦":"2018-06-04","価格":482.0,"reg1":569.397},{"品目名":"きゅうり","品目コード":"06","調査期間_西暦":"2018-06-11","価格":471.0,"reg1":569.608},{"品目名":"きゅうり","品目コード":"06","調査期間_西暦":"2018-06-18","価格":483.0,"reg1":569.82},{"品目名":"きゅうり","品目コード":"06","調査期間_西暦":"2018-06-25","価格":524.0,"reg1":570.031},{"品目名":"きゅうり","品目コード":"06","調査期間_西暦":"2018-07-02","価格":512.0,"reg1":570.242},{"品目名":"きゅうり","品目コード":"06","調査期間_西暦":"2018-07-09","価格":534.0,"reg1":570.454},{"品目名":"きゅうり","品目コード":"06","調査期間_西暦":"2018-07-16","価格":791.0,"reg1":570.665},{"品目名":"きゅうり","品目コード":"06","調査期間_西暦":"2018-07-23","価格":712.0,"reg1":570.877},{"品目名":"きゅうり","品目コード":"06","調査期間_西暦":"2018-07-30","価格":658.0,"reg1":571.088},{"品目名":"きゅうり","品目コード":"06","調査期間_西暦":"2018-08-06","価格":629.0,"reg1":571.3},{"品目名":"きゅうり","品目コード":"06","調査期間_西暦":"2018-08-13","価格":708.0,"reg1":571.511},{"品目名":"きゅうり","品目コード":"06","調査期間_西暦":"2018-08-20","価格":703.0,"reg1":571.723},{"品目名":"きゅうり","品目コード":"06","調査期間_西暦":"2018-08-27","価格":765.0,"reg1":571.934},{"品目名":"きゅうり","品目コード":"06","調査期間_西暦":"2018-09-03","価格":740.0,"reg1":572.145},{"品目名":"きゅうり","品目コード":"06","調査期間_西暦":"2018-09-10","価格":746.0,"reg1":572.357},{"品目名":"きゅうり","品目コード":"06","調査期間_西暦":"2018-09-17","価格":754.0,"reg1":572.568},{"品目名":"きゅうり","品目コード":"06","調査期間_西暦":"2018-09-24","価格":734.0,"reg1":572.78},{"品目名":"きゅうり","品目コード":"06","調査期間_西暦":"2018-10-01","価格":null,"reg1":null},{"品目名":"きゅうり","品目コード":"06","調査期間_西暦":"2018-10-08","価格":null,"reg1":null},{"品目名":"きゅうり","品目コード":"06","調査期間_西暦":"2018-10-15","価格":null,"reg1":null},{"品目名":"きゅうり","品目コード":"06","調査期間_西暦":"2018-10-22","価格":null,"reg1":null},{"品目名":"きゅうり","品目コード":"06","調査期間_西暦":"2018-10-29","価格":null,"reg1":null},{"品目名":"きゅうり","品目コード":"06","調査期間_西暦":"2018-11-05","価格":null,"reg1":null},{"品目名":"きゅうり","品目コード":"06","調査期間_西暦":"2018-11-12","価格":null,"reg1":null},{"品目名":"きゅうり","品目コード":"06","調査期間_西暦":"2018-11-19","価格":null,"reg1":null},{"品目名":"きゅうり","品目コード":"06","調査期間_西暦":"2018-11-26","価格":null,"reg1":null},{"品目名":"きゅうり","品目コード":"06","調査期間_西暦":"2018-12-03","価格":null,"reg1":null},{"品目名":"きゅうり","品目コード":"06","調査期間_西暦":"2018-12-10","価格":null,"reg1":null},{"品目名":"きゅうり","品目コード":"06","調査期間_西暦":"2018-12-17","価格":null,"reg1":null},{"品目名":"きゅうり","品目コード":"06","調査期間_西暦":"2018-12-24","価格":null,"reg1":null},{"品目名":"きゅうり","品目コード":"06","調査期間_西暦":"2019-01-07","価格":null,"reg1":null},{"品目名":"きゅうり","品目コード":"06","調査期間_西暦":"2019-01-14","価格":null,"reg1":null},{"品目名":"きゅうり","品目コード":"06","調査期間_西暦":"2019-01-21","価格":null,"reg1":null},{"品目名":"きゅうり","品目コード":"06","調査期間_西暦":"2019-01-28","価格":null,"reg1":null},{"品目名":"きゅうり","品目コード":"06","調査期間_西暦":"2019-02-04","価格":null,"reg1":null},{"品目名":"きゅうり","品目コード":"06","調査期間_西暦":"2019-02-11","価格":null,"reg1":null},{"品目名":"きゅうり","品目コード":"06","調査期間_西暦":"2019-02-18","価格":null,"reg1":null},{"品目名":"きゅうり","品目コード":"06","調査期間_西暦":"2019-02-25","価格":null,"reg1":null},{"品目名":"きゅうり","品目コード":"06","調査期間_西暦":"2019-03-04","価格":null,"reg1":null},{"品目名":"きゅうり","品目コード":"06","調査期間_西暦":"2019-03-11","価格":null,"reg1":null},{"品目名":"きゅうり","品目コード":"06","調査期間_西暦":"2019-03-18","価格":null,"reg1":null},{"品目名":"きゅうり","品目コード":"06","調査期間_西暦":"2019-03-25","価格":null,"reg1":null},{"品目名":"きゅうり","品目コード":"06","調査期間_西暦":"2019-04-01","価格":550.0,"reg1":578.277},{"品目名":"きゅうり","品目コード":"06","調査期間_西暦":"2019-04-08","価格":510.0,"reg1":578.489},{"品目名":"きゅうり","品目コード":"06","調査期間_西暦":"2019-04-15","価格":490.0,"reg1":578.7},{"品目名":"きゅうり","品目コード":"06","調査期間_西暦":"2019-04-22","価格":479.0,"reg1":578.911},{"品目名":"きゅうり","品目コード":"06","調査期間_西暦":"2019-05-06","価格":440.0,"reg1":579.123},{"品目名":"きゅうり","品目コード":"06","調査期間_西暦":"2019-05-13","価格":461.0,"reg1":579.334},{"品目名":"きゅうり","品目コード":"06","調査期間_西暦":"2019-05-20","価格":455.0,"reg1":579.546},{"品目名":"きゅうり","品目コード":"06","調査期間_西暦":"2019-05-27","価格":451.0,"reg1":579.757},{"品目名":"きゅうり","品目コード":"06","調査期間_西暦":"2019-06-03","価格":441.0,"reg1":579.969},{"品目名":"きゅうり","品目コード":"06","調査期間_西暦":"2019-06-10","価格":449.0,"reg1":580.18},{"品目名":"きゅうり","品目コード":"06","調査期間_西暦":"2019-06-17","価格":482.0,"reg1":580.392},{"品目名":"きゅうり","品目コード":"06","調査期間_西暦":"2019-06-24","価格":507.0,"reg1":580.603},{"品目名":"きゅうり","品目コード":"06","調査期間_西暦":"2019-07-01","価格":495.0,"reg1":580.814},{"品目名":"きゅうり","品目コード":"06","調査期間_西暦":"2019-07-08","価格":490.0,"reg1":581.026},{"品目名":"きゅうり","品目コード":"06","調査期間_西暦":"2019-07-15","価格":605.0,"reg1":581.237},{"品目名":"きゅうり","品目コード":"06","調査期間_西暦":"2019-07-22","価格":609.0,"reg1":581.449},{"品目名":"きゅうり","品目コード":"06","調査期間_西暦":"2019-07-29","価格":558.0,"reg1":581.66},{"品目名":"きゅうり","品目コード":"06","調査期間_西暦":"2019-08-05","価格":513.0,"reg1":581.872},{"品目名":"きゅうり","品目コード":"06","調査期間_西暦":"2019-08-12","価格":561.0,"reg1":582.083},{"品目名":"きゅうり","品目コード":"06","調査期間_西暦":"2019-08-19","価格":593.0,"reg1":582.294},{"品目名":"きゅうり","品目コード":"06","調査期間_西暦":"2019-08-26","価格":621.0,"reg1":582.506},{"品目名":"きゅうり","品目コード":"06","調査期間_西暦":"2019-09-02","価格":746.0,"reg1":582.717},{"品目名":"きゅうり","品目コード":"06","調査期間_西暦":"2019-09-09","価格":749.0,"reg1":582.929},{"品目名":"きゅうり","品目コード":"06","調査期間_西暦":"2019-09-16","価格":644.0,"reg1":583.14},{"品目名":"きゅうり","品目コード":"06","調査期間_西暦":"2019-09-23","価格":594.0,"reg1":583.352},{"品目名":"きゅうり","品目コード":"06","調査期間_西暦":"2019-09-30","価格":592.0,"reg1":583.563},{"品目名":"きゅうり","品目コード":"06","調査期間_西暦":"2019-10-07","価格":null,"reg1":null},{"品目名":"きゅうり","品目コード":"06","調査期間_西暦":"2019-10-14","価格":null,"reg1":null},{"品目名":"きゅうり","品目コード":"06","調査期間_西暦":"2019-10-21","価格":null,"reg1":null},{"品目名":"きゅうり","品目コード":"06","調査期間_西暦":"2019-10-28","価格":null,"reg1":null},{"品目名":"きゅうり","品目コード":"06","調査期間_西暦":"2019-11-04","価格":null,"reg1":null},{"品目名":"きゅうり","品目コード":"06","調査期間_西暦":"2019-11-11","価格":null,"reg1":null},{"品目名":"きゅうり","品目コード":"06","調査期間_西暦":"2019-11-18","価格":null,"reg1":null},{"品目名":"きゅうり","品目コード":"06","調査期間_西暦":"2019-11-25","価格":null,"reg1":null},{"品目名":"きゅうり","品目コード":"06","調査期間_西暦":"2019-12-02","価格":null,"reg1":null},{"品目名":"きゅうり","品目コード":"06","調査期間_西暦":"2019-12-09","価格":null,"reg1":null},{"品目名":"きゅうり","品目コード":"06","調査期間_西暦":"2019-12-16","価格":null,"reg1":null},{"品目名":"きゅうり","品目コード":"06","調査期間_西暦":"2019-12-23","価格":null,"reg1":null},{"品目名":"きゅうり","品目コード":"06","調査期間_西暦":"2020-01-06","価格":null,"reg1":null},{"品目名":"きゅうり","品目コード":"06","調査期間_西暦":"2020-01-13","価格":null,"reg1":null},{"品目名":"きゅうり","品目コード":"06","調査期間_西暦":"2020-01-20","価格":null,"reg1":null},{"品目名":"きゅうり","品目コード":"06","調査期間_西暦":"2020-01-27","価格":null,"reg1":null},{"品目名":"きゅうり","品目コード":"06","調査期間_西暦":"2020-02-03","価格":null,"reg1":null},{"品目名":"きゅうり","品目コード":"06","調査期間_西暦":"2020-02-10","価格":null,"reg1":null},{"品目名":"きゅうり","品目コード":"06","調査期間_西暦":"2020-02-17","価格":null,"reg1":null},{"品目名":"きゅうり","品目コード":"06","調査期間_西暦":"2020-02-24","価格":null,"reg1":null},{"品目名":"きゅうり","品目コード":"06","調査期間_西暦":"2020-03-02","価格":null,"reg1":null},{"品目名":"きゅうり","品目コード":"06","調査期間_西暦":"2020-03-09","価格":null,"reg1":null},{"品目名":"きゅうり","品目コード":"06","調査期間_西暦":"2020-03-16","価格":null,"reg1":null},{"品目名":"きゅうり","品目コード":"06","調査期間_西暦":"2020-03-23","価格":null,"reg1":null},{"品目名":"きゅうり","品目コード":"06","調査期間_西暦":"2020-03-30","価格":null,"reg1":null},{"品目名":"きゅうり","品目コード":"06","調査期間_西暦":"2020-04-06","価格":596.0,"reg1":589.061},{"品目名":"きゅうり","品目コード":"06","調査期間_西暦":"2020-04-13","価格":613.0,"reg1":589.272},{"品目名":"きゅうり","品目コード":"06","調査期間_西暦":"2020-04-20","価格":null,"reg1":null},{"品目名":"きゅうり","品目コード":"06","調査期間_西暦":"2020-04-27","価格":null,"reg1":null},{"品目名":"きゅうり","品目コード":"06","調査期間_西暦":"2020-05-11","価格":513.0,"reg1":589.906},{"品目名":"きゅうり","品目コード":"06","調査期間_西暦":"2020-05-18","価格":481.0,"reg1":590.118},{"品目名":"きゅうり","品目コード":"06","調査期間_西暦":"2020-05-25","価格":511.0,"reg1":590.329},{"品目名":"きゅうり","品目コード":"06","調査期間_西暦":"2020-06-01","価格":539.0,"reg1":590.541},{"品目名":"きゅうり","品目コード":"06","調査期間_西暦":"2020-06-08","価格":525.0,"reg1":590.752},{"品目名":"きゅうり","品目コード":"06","調査期間_西暦":"2020-06-15","価格":509.0,"reg1":590.964},{"品目名":"きゅうり","品目コード":"06","調査期間_西暦":"2020-06-22","価格":519.0,"reg1":591.175},{"品目名":"きゅうり","品目コード":"06","調査期間_西暦":"2020-06-29","価格":576.0,"reg1":591.386},{"品目名":"きゅうり","品目コード":"06","調査期間_西暦":"2020-07-06","価格":575.0,"reg1":591.598},{"品目名":"きゅうり","品目コード":"06","調査期間_西暦":"2020-07-13","価格":588.0,"reg1":591.809},{"品目名":"きゅうり","品目コード":"06","調査期間_西暦":"2020-07-20","価格":672.0,"reg1":592.021},{"品目名":"きゅうり","品目コード":"06","調査期間_西暦":"2020-07-27","価格":738.0,"reg1":592.232},{"品目名":"きゅうり","品目コード":"06","調査期間_西暦":"2020-08-03","価格":723.0,"reg1":592.444},{"品目名":"きゅうり","品目コード":"06","調査期間_西暦":"2020-08-10","価格":717.0,"reg1":592.655},{"品目名":"きゅうり","品目コード":"06","調査期間_西暦":"2020-08-17","価格":710.0,"reg1":592.866},{"品目名":"きゅうり","品目コード":"06","調査期間_西暦":"2020-08-24","価格":704.0,"reg1":593.078},{"品目名":"きゅうり","品目コード":"06","調査期間_西暦":"2020-08-31","価格":685.0,"reg1":593.289},{"品目名":"きゅうり","品目コード":"06","調査期間_西暦":"2020-09-07","価格":668.0,"reg1":593.501},{"品目名":"きゅうり","品目コード":"06","調査期間_西暦":"2020-09-14","価格":659.0,"reg1":593.712},{"品目名":"きゅうり","品目コード":"06","調査期間_西暦":"2020-09-21","価格":710.0,"reg1":593.924},{"品目名":"きゅうり","品目コード":"06","調査期間_西暦":"2020-09-28","価格":707.0,"reg1":594.135},{"品目名":"きゅうり","品目コード":"06","調査期間_西暦":"2020-10-05","価格":null,"reg1":null},{"品目名":"きゅうり","品目コード":"06","調査期間_西暦":"2020-10-12","価格":null,"reg1":null},{"品目名":"きゅうり","品目コード":"06","調査期間_西暦":"2020-10-19","価格":null,"reg1":null},{"品目名":"きゅうり","品目コード":"06","調査期間_西暦":"2020-10-26","価格":null,"reg1":null},{"品目名":"きゅうり","品目コード":"06","調査期間_西暦":"2020-11-02","価格":null,"reg1":null},{"品目名":"きゅうり","品目コード":"06","調査期間_西暦":"2020-11-09","価格":null,"reg1":null},{"品目名":"きゅうり","品目コード":"06","調査期間_西暦":"2020-11-16","価格":null,"reg1":null},{"品目名":"きゅうり","品目コード":"06","調査期間_西暦":"2020-11-23","価格":null,"reg1":null},{"品目名":"きゅうり","品目コード":"06","調査期間_西暦":"2020-11-30","価格":null,"reg1":null},{"品目名":"きゅうり","品目コード":"06","調査期間_西暦":"2020-12-07","価格":null,"reg1":null},{"品目名":"きゅうり","品目コード":"06","調査期間_西暦":"2020-12-14","価格":null,"reg1":null},{"品目名":"きゅうり","品目コード":"06","調査期間_西暦":"2020-12-21","価格":null,"reg1":null},{"品目名":"きゅうり","品目コード":"06","調査期間_西暦":"2021-01-04","価格":null,"reg1":null},{"品目名":"きゅうり","品目コード":"06","調査期間_西暦":"2021-01-11","価格":null,"reg1":null},{"品目名":"きゅうり","品目コード":"06","調査期間_西暦":"2021-01-18","価格":null,"reg1":null},{"品目名":"きゅうり","品目コード":"06","調査期間_西暦":"2021-01-25","価格":null,"reg1":null},{"品目名":"きゅうり","品目コード":"06","調査期間_西暦":"2021-02-01","価格":null,"reg1":null},{"品目名":"きゅうり","品目コード":"06","調査期間_西暦":"2021-02-08","価格":null,"reg1":null},{"品目名":"きゅうり","品目コード":"06","調査期間_西暦":"2021-02-15","価格":null,"reg1":null},{"品目名":"きゅうり","品目コード":"06","調査期間_西暦":"2021-02-22","価格":null,"reg1":null},{"品目名":"きゅうり","品目コード":"06","調査期間_西暦":"2021-03-01","価格":null,"reg1":null},{"品目名":"きゅうり","品目コード":"06","調査期間_西暦":"2021-03-08","価格":null,"reg1":null},{"品目名":"きゅうり","品目コード":"06","調査期間_西暦":"2021-03-15","価格":null,"reg1":null},{"品目名":"きゅうり","品目コード":"06","調査期間_西暦":"2021-03-22","価格":null,"reg1":null},{"品目名":"きゅうり","品目コード":"06","調査期間_西暦":"2021-03-29","価格":null,"reg1":null},{"品目名":"きゅうり","品目コード":"06","調査期間_西暦":"2021-04-05","価格":523.0,"reg1":599.633},{"品目名":"きゅうり","品目コード":"06","調査期間_西暦":"2021-04-12","価格":519.0,"reg1":599.844},{"品目名":"きゅうり","品目コード":"06","調査期間_西暦":"2021-04-19","価格":504.0,"reg1":600.055},{"品目名":"きゅうり","品目コード":"06","調査期間_西暦":"2021-04-26","価格":506.0,"reg1":600.267},{"品目名":"きゅうり","品目コード":"06","調査期間_西暦":"2021-05-10","価格":480.0,"reg1":600.478},{"品目名":"きゅうり","品目コード":"06","調査期間_西暦":"2021-05-17","価格":460.0,"reg1":600.69},{"品目名":"きゅうり","品目コード":"06","調査期間_西暦":"2021-05-24","価格":473.0,"reg1":600.901},{"品目名":"きゅうり","品目コード":"06","調査期間_西暦":"2021-05-31","価格":648.0,"reg1":601.113},{"品目名":"きゅうり","品目コード":"06","調査期間_西暦":"2021-06-07","価格":593.0,"reg1":601.324},{"品目名":"きゅうり","品目コード":"06","調査期間_西暦":"2021-06-14","価格":545.0,"reg1":601.536},{"品目名":"きゅうり","品目コード":"06","調査期間_西暦":"2021-06-21","価格":510.0,"reg1":601.747},{"品目名":"きゅうり","品目コード":"06","調査期間_西暦":"2021-06-28","価格":503.0,"reg1":601.958},{"品目名":"きゅうり","品目コード":"06","調査期間_西暦":"2021-07-05","価格":459.0,"reg1":602.17},{"品目名":"きゅうり","品目コード":"06","調査期間_西暦":"2021-07-12","価格":450.0,"reg1":602.381},{"品目名":"きゅうり","品目コード":"06","調査期間_西暦":"2021-07-19","価格":456.0,"reg1":602.593},{"品目名":"きゅうり","品目コード":"06","調査期間_西暦":"2021-07-26","価格":468.0,"reg1":602.804},{"品目名":"きゅうり","品目コード":"06","調査期間_西暦":"2021-08-02","価格":461.0,"reg1":603.016},{"品目名":"きゅうり","品目コード":"06","調査期間_西暦":"2021-08-09","価格":461.0,"reg1":603.227},{"品目名":"きゅうり","品目コード":"06","調査期間_西暦":"2021-08-16","価格":557.0,"reg1":603.438},{"品目名":"きゅうり","品目コード":"06","調査期間_西暦":"2021-08-23","価格":919.0,"reg1":603.65},{"品目名":"きゅうり","品目コード":"06","調査期間_西暦":"2021-08-30","価格":894.0,"reg1":603.861},{"品目名":"きゅうり","品目コード":"06","調査期間_西暦":"2021-09-06","価格":753.0,"reg1":604.073},{"品目名":"きゅうり","品目コード":"06","調査期間_西暦":"2021-09-13","価格":747.0,"reg1":604.284},{"品目名":"きゅうり","品目コード":"06","調査期間_西暦":"2021-09-20","価格":706.0,"reg1":604.496},{"品目名":"きゅうり","品目コード":"06","調査期間_西暦":"2021-09-27","価格":682.0,"reg1":604.707},{"品目名":"きゅうり","品目コード":"06","調査期間_西暦":"2021-10-04","価格":null,"reg1":null},{"品目名":"きゅうり","品目コード":"06","調査期間_西暦":"2021-10-11","価格":null,"reg1":null},{"品目名":"きゅうり","品目コード":"06","調査期間_西暦":"2021-10-18","価格":null,"reg1":null},{"品目名":"きゅうり","品目コード":"06","調査期間_西暦":"2021-10-25","価格":null,"reg1":null},{"品目名":"きゅうり","品目コード":"06","調査期間_西暦":"2021-11-01","価格":null,"reg1":null},{"品目名":"きゅうり","品目コード":"06","調査期間_西暦":"2021-11-08","価格":null,"reg1":null},{"品目名":"きゅうり","品目コード":"06","調査期間_西暦":"2021-11-15","価格":null,"reg1":null},{"品目名":"きゅうり","品目コード":"06","調査期間_西暦":"2021-11-22","価格":null,"reg1":null},{"品目名":"きゅうり","品目コード":"06","調査期間_西暦":"2021-11-29","価格":null,"reg1":null},{"品目名":"きゅうり","品目コード":"06","調査期間_西暦":"2021-12-06","価格":null,"reg1":null},{"品目名":"きゅうり","品目コード":"06","調査期間_西暦":"2021-12-13","価格":null,"reg1":null},{"品目名":"きゅうり","品目コード":"06","調査期間_西暦":"2021-12-20","価格":null,"reg1":null},{"品目名":"きゅうり","品目コード":"06","調査期間_西暦":"2022-01-03","価格":null,"reg1":null},{"品目名":"きゅうり","品目コード":"06","調査期間_西暦":"2022-01-10","価格":null,"reg1":null},{"品目名":"きゅうり","品目コード":"06","調査期間_西暦":"2022-01-17","価格":null,"reg1":null},{"品目名":"きゅうり","品目コード":"06","調査期間_西暦":"2022-01-24","価格":null,"reg1":null},{"品目名":"きゅうり","品目コード":"06","調査期間_西暦":"2022-01-31","価格":null,"reg1":null},{"品目名":"きゅうり","品目コード":"06","調査期間_西暦":"2022-02-07","価格":null,"reg1":null},{"品目名":"きゅうり","品目コード":"06","調査期間_西暦":"2022-02-14","価格":null,"reg1":null},{"品目名":"きゅうり","品目コード":"06","調査期間_西暦":"2022-02-21","価格":null,"reg1":null},{"品目名":"きゅうり","品目コード":"06","調査期間_西暦":"2022-02-28","価格":null,"reg1":null},{"品目名":"きゅうり","品目コード":"06","調査期間_西暦":"2022-03-07","価格":null,"reg1":null},{"品目名":"きゅうり","品目コード":"06","調査期間_西暦":"2022-03-14","価格":null,"reg1":null},{"品目名":"きゅうり","品目コード":"06","調査期間_西暦":"2022-03-21","価格":null,"reg1":null},{"品目名":"きゅうり","品目コード":"06","調査期間_西暦":"2022-03-28","価格":null,"reg1":null},{"品目名":"きゅうり","品目コード":"06","調査期間_西暦":"2022-04-04","価格":520.0,"reg1":610.205},{"品目名":"きゅうり","品目コード":"06","調査期間_西暦":"2022-04-11","価格":526.0,"reg1":610.416},{"品目名":"きゅうり","品目コード":"06","調査期間_西暦":"2022-04-18","価格":510.0,"reg1":610.627},{"品目名":"きゅうり","品目コード":"06","調査期間_西暦":"2022-04-25","価格":511.0,"reg1":610.839},{"品目名":"きゅうり","品目コード":"06","調査期間_西暦":"2022-05-09","価格":532.0,"reg1":611.05},{"品目名":"きゅうり","品目コード":"06","調査期間_西暦":"2022-05-16","価格":519.0,"reg1":611.262},{"品目名":"きゅうり","品目コード":"06","調査期間_西暦":"2022-05-23","価格":510.0,"reg1":611.473},{"品目名":"きゅうり","品目コード":"06","調査期間_西暦":"2022-05-30","価格":524.0,"reg1":611.685},{"品目名":"きゅうり","品目コード":"06","調査期間_西暦":"2022-06-06","価格":498.0,"reg1":611.896},{"品目名":"きゅうり","品目コード":"06","調査期間_西暦":"2022-06-13","価格":487.0,"reg1":612.107},{"品目名":"きゅうり","品目コード":"06","調査期間_西暦":"2022-06-20","価格":482.0,"reg1":612.319},{"品目名":"きゅうり","品目コード":"06","調査期間_西暦":"2022-06-27","価格":462.0,"reg1":612.53},{"品目名":"きゅうり","品目コード":"06","調査期間_西暦":"2022-07-04","価格":455.0,"reg1":612.742},{"品目名":"きゅうり","品目コード":"06","調査期間_西暦":"2022-07-11","価格":495.0,"reg1":612.953},{"品目名":"きゅうり","品目コード":"06","調査期間_西暦":"2022-07-18","価格":541.0,"reg1":613.165},{"品目名":"きゅうり","品目コード":"06","調査期間_西暦":"2022-07-25","価格":555.0,"reg1":613.376},{"品目名":"きゅうり","品目コード":"06","調査期間_西暦":"2022-08-01","価格":533.0,"reg1":613.588},{"品目名":"きゅうり","品目コード":"06","調査期間_西暦":"2022-08-08","価格":538.0,"reg1":613.799},{"品目名":"きゅうり","品目コード":"06","調査期間_西暦":"2022-08-15","価格":576.0,"reg1":614.01},{"品目名":"きゅうり","品目コード":"06","調査期間_西暦":"2022-08-22","価格":562.0,"reg1":614.222},{"品目名":"きゅうり","品目コード":"06","調査期間_西暦":"2022-08-29","価格":583.0,"reg1":614.433},{"品目名":"きゅうり","品目コード":"06","調査期間_西暦":"2022-09-05","価格":627.0,"reg1":614.645},{"品目名":"きゅうり","品目コード":"06","調査期間_西暦":"2022-09-12","価格":618.0,"reg1":614.856},{"品目名":"きゅうり","品目コード":"06","調査期間_西暦":"2022-09-19","価格":591.0,"reg1":615.068},{"品目名":"きゅうり","品目コード":"06","調査期間_西暦":"2022-09-26","価格":602.0,"reg1":615.279},{"品目名":"きゅうり","品目コード":"06","調査期間_西暦":"2022-10-03","価格":null,"reg1":null},{"品目名":"きゅうり","品目コード":"06","調査期間_西暦":"2022-10-10","価格":null,"reg1":null},{"品目名":"きゅうり","品目コード":"06","調査期間_西暦":"2022-10-17","価格":null,"reg1":null},{"品目名":"きゅうり","品目コード":"06","調査期間_西暦":"2022-10-24","価格":null,"reg1":null},{"品目名":"きゅうり","品目コード":"06","調査期間_西暦":"2022-10-31","価格":null,"reg1":null},{"品目名":"きゅうり","品目コード":"06","調査期間_西暦":"2022-11-07","価格":null,"reg1":null},{"品目名":"きゅうり","品目コード":"06","調査期間_西暦":"2022-11-14","価格":null,"reg1":null},{"品目名":"きゅうり","品目コード":"06","調査期間_西暦":"2022-11-21","価格":null,"reg1":null},{"品目名":"きゅうり","品目コード":"06","調査期間_西暦":"2022-11-28","価格":null,"reg1":null},{"品目名":"きゅうり","品目コード":"06","調査期間_西暦":"2022-12-05","価格":null,"reg1":null},{"品目名":"きゅうり","品目コード":"06","調査期間_西暦":"2022-12-12","価格":null,"reg1":null},{"品目名":"きゅうり","品目コード":"06","調査期間_西暦":"2022-12-19","価格":null,"reg1":null},{"品目名":"きゅうり","品目コード":"06","調査期間_西暦":"2022-12-26","価格":null,"reg1":null},{"品目名":"きゅうり","品目コード":"06","調査期間_西暦":"2023-01-09","価格":null,"reg1":null},{"品目名":"きゅうり","品目コード":"06","調査期間_西暦":"2023-01-16","価格":null,"reg1":null},{"品目名":"きゅうり","品目コード":"06","調査期間_西暦":"2023-01-23","価格":null,"reg1":null},{"品目名":"きゅうり","品目コード":"06","調査期間_西暦":"2023-01-30","価格":null,"reg1":null},{"品目名":"きゅうり","品目コード":"06","調査期間_西暦":"2023-02-06","価格":null,"reg1":null},{"品目名":"きゅうり","品目コード":"06","調査期間_西暦":"2023-02-13","価格":null,"reg1":null},{"品目名":"きゅうり","品目コード":"06","調査期間_西暦":"2023-02-20","価格":null,"reg1":null},{"品目名":"きゅうり","品目コード":"06","調査期間_西暦":"2023-02-27","価格":null,"reg1":null},{"品目名":"きゅうり","品目コード":"06","調査期間_西暦":"2023-03-06","価格":null,"reg1":null},{"品目名":"きゅうり","品目コード":"06","調査期間_西暦":"2023-03-13","価格":null,"reg1":null},{"品目名":"きゅうり","品目コード":"06","調査期間_西暦":"2023-03-20","価格":null,"reg1":null},{"品目名":"きゅうり","品目コード":"06","調査期間_西暦":"2023-03-27","価格":null,"reg1":null},{"品目名":"きゅうり","品目コード":"06","調査期間_西暦":"2023-04-03","価格":595.0,"reg1":620.777},{"品目名":"きゅうり","品目コード":"06","調査期間_西暦":"2023-04-10","価格":616.0,"reg1":620.988},{"品目名":"きゅうり","品目コード":"06","調査期間_西暦":"2023-04-17","価格":593.0,"reg1":621.199},{"品目名":"きゅうり","品目コード":"06","調査期間_西暦":"2023-04-24","価格":593.0,"reg1":621.411},{"品目名":"きゅうり","品目コード":"06","調査期間_西暦":"2023-05-08","価格":574.0,"reg1":621.622},{"品目名":"きゅうり","品目コード":"06","調査期間_西暦":"2023-05-15","価格":542.0,"reg1":621.834},{"品目名":"きゅうり","品目コード":"06","調査期間_西暦":"2023-05-22","価格":532.0,"reg1":622.045},{"品目名":"きゅうり","品目コード":"06","調査期間_西暦":"2023-05-29","価格":496.0,"reg1":622.257},{"品目名":"きゅうり","品目コード":"06","調査期間_西暦":"2023-06-05","価格":497.0,"reg1":622.468},{"品目名":"きゅうり","品目コード":"06","調査期間_西暦":"2023-06-12","価格":538.0,"reg1":622.679},{"品目名":"きゅうり","品目コード":"06","調査期間_西暦":"2023-06-19","価格":554.0,"reg1":622.891},{"品目名":"きゅうり","品目コード":"06","調査期間_西暦":"2023-06-26","価格":583.0,"reg1":623.102},{"品目名":"きゅうり","品目コード":"06","調査期間_西暦":"2023-07-03","価格":583.0,"reg1":623.314},{"品目名":"きゅうり","品目コード":"06","調査期間_西暦":"2023-07-10","価格":585.0,"reg1":623.525},{"品目名":"きゅうり","品目コード":"06","調査期間_西暦":"2023-07-17","価格":600.0,"reg1":623.737},{"品目名":"きゅうり","品目コード":"06","調査期間_西暦":"2023-07-24","価格":613.0,"reg1":623.948},{"品目名":"きゅうり","品目コード":"06","調査期間_西暦":"2023-07-31","価格":619.0,"reg1":624.16},{"品目名":"きゅうり","品目コード":"06","調査期間_西暦":"2023-08-07","価格":612.0,"reg1":624.371},{"品目名":"きゅうり","品目コード":"06","調査期間_西暦":"2023-08-14","価格":654.0,"reg1":624.582},{"品目名":"きゅうり","品目コード":"06","調査期間_西暦":"2023-08-21","価格":665.0,"reg1":624.794},{"品目名":"きゅうり","品目コード":"06","調査期間_西暦":"2023-08-28","価格":735.0,"reg1":625.005},{"品目名":"きゅうり","品目コード":"06","調査期間_西暦":"2023-09-04","価格":741.0,"reg1":625.217},{"品目名":"きゅうり","品目コード":"06","調査期間_西暦":"2023-09-11","価格":736.0,"reg1":625.428},{"品目名":"きゅうり","品目コード":"06","調査期間_西暦":"2023-09-18","価格":716.0,"reg1":625.64},{"品目名":"きゅうり","品目コード":"06","調査期間_西暦":"2023-09-25","価格":685.0,"reg1":625.851},{"品目名":"きゅうり","品目コード":"06","調査期間_西暦":"2023-10-02","価格":null,"reg1":null},{"品目名":"きゅうり","品目コード":"06","調査期間_西暦":"2023-10-09","価格":null,"reg1":null},{"品目名":"きゅうり","品目コード":"06","調査期間_西暦":"2023-10-16","価格":null,"reg1":null},{"品目名":"きゅうり","品目コード":"06","調査期間_西暦":"2023-10-23","価格":null,"reg1":null},{"品目名":"きゅうり","品目コード":"06","調査期間_西暦":"2023-10-30","価格":null,"reg1":null},{"品目名":"きゅうり","品目コード":"06","調査期間_西暦":"2023-11-06","価格":null,"reg1":null},{"品目名":"きゅうり","品目コード":"06","調査期間_西暦":"2023-11-13","価格":null,"reg1":null},{"品目名":"きゅうり","品目コード":"06","調査期間_西暦":"2023-11-20","価格":null,"reg1":null},{"品目名":"きゅうり","品目コード":"06","調査期間_西暦":"2023-11-27","価格":null,"reg1":null},{"品目名":"きゅうり","品目コード":"06","調査期間_西暦":"2023-12-04","価格":null,"reg1":null},{"品目名":"きゅうり","品目コード":"06","調査期間_西暦":"2023-12-11","価格":null,"reg1":null},{"品目名":"きゅうり","品目コード":"06","調査期間_西暦":"2023-12-18","価格":null,"reg1":null},{"品目名":"きゅうり","品目コード":"06","調査期間_西暦":"2023-12-25","価格":null,"reg1":null},{"品目名":"きゅうり","品目コード":"06","調査期間_西暦":"2024-01-08","価格":null,"reg1":null},{"品目名":"きゅうり","品目コード":"06","調査期間_西暦":"2024-01-15","価格":null,"reg1":null},{"品目名":"きゅうり","品目コード":"06","調査期間_西暦":"2024-01-22","価格":null,"reg1":null},{"品目名":"きゅうり","品目コード":"06","調査期間_西暦":"2024-01-29","価格":null,"reg1":null},{"品目名":"きゅうり","品目コード":"06","調査期間_西暦":"2024-02-05","価格":null,"reg1":null},{"品目名":"きゅうり","品目コード":"06","調査期間_西暦":"2024-02-12","価格":null,"reg1":null},{"品目名":"きゅうり","品目コード":"06","調査期間_西暦":"2024-02-19","価格":null,"reg1":null},{"品目名":"きゅうり","品目コード":"06","調査期間_西暦":"2024-02-26","価格":null,"reg1":null},{"品目名":"きゅうり","品目コード":"06","調査期間_西暦":"2024-03-04","価格":null,"reg1":null},{"品目名":"きゅうり","品目コード":"06","調査期間_西暦":"2024-03-11","価格":null,"reg1":null},{"品目名":"きゅうり","品目コード":"06","調査期間_西暦":"2024-03-18","価格":null,"reg1":null},{"品目名":"きゅうり","品目コード":"06","調査期間_西暦":"2024-03-25","価格":null,"reg1":null},{"品目名":"きゅうり","品目コード":"06","調査期間_西暦":"2024-04-01","価格":702.0,"reg1":631.349},{"品目名":"きゅうり","品目コード":"06","調査期間_西暦":"2024-04-08","価格":697.0,"reg1":631.56},{"品目名":"きゅうり","品目コード":"06","調査期間_西暦":"2024-04-15","価格":697.0,"reg1":631.771},{"品目名":"きゅうり","品目コード":"06","調査期間_西暦":"2024-04-22","価格":710.0,"reg1":631.983},{"品目名":"きゅうり","品目コード":"06","調査期間_西暦":"2024-05-06","価格":672.0,"reg1":632.194},{"品目名":"きゅうり","品目コード":"06","調査期間_西暦":"2024-05-13","価格":663.0,"reg1":632.406},{"品目名":"きゅうり","品目コード":"06","調査期間_西暦":"2024-05-20","価格":659.0,"reg1":632.617},{"品目名":"きゅうり","品目コード":"06","調査期間_西暦":"2024-05-27","価格":631.0,"reg1":632.829},{"品目名":"きゅうり","品目コード":"06","調査期間_西暦":"2024-06-03","価格":592.0,"reg1":633.04},{"品目名":"きゅうり","品目コード":"06","調査期間_西暦":"2024-06-10","価格":582.0,"reg1":633.251},{"品目名":"きゅうり","品目コード":"06","調査期間_西暦":"2024-06-17","価格":553.0,"reg1":633.463},{"品目名":"きゅうり","品目コード":"06","調査期間_西暦":"2024-06-24","価格":539.0,"reg1":633.674},{"品目名":"きゅうり","品目コード":"06","調査期間_西暦":"2024-07-01","価格":540.0,"reg1":633.886},{"品目名":"きゅうり","品目コード":"06","調査期間_西暦":"2024-07-08","価格":640.0,"reg1":634.097},{"品目名":"きゅうり","品目コード":"06","調査期間_西暦":"2024-07-15","価格":689.0,"reg1":634.309},{"品目名":"きゅうり","品目コード":"06","調査期間_西暦":"2024-07-22","価格":745.0,"reg1":634.52},{"品目名":"きゅうり","品目コード":"06","調査期間_西暦":"2024-07-29","価格":752.0,"reg1":634.732},{"品目名":"きゅうり","品目コード":"06","調査期間_西暦":"2024-08-05","価格":744.0,"reg1":634.943},{"品目名":"きゅうり","品目コード":"06","調査期間_西暦":"2024-08-19","価格":788.0,"reg1":635.154},{"品目名":"きゅうり","品目コード":"06","調査期間_西暦":"2024-08-26","価格":755.0,"reg1":635.366},{"品目名":"きゅうり","品目コード":"06","調査期間_西暦":"2024-09-02","価格":783.0,"reg1":635.577},{"品目名":"きゅうり","品目コード":"06","調査期間_西暦":"2024-09-09","価格":863.0,"reg1":635.789},{"品目名":"きゅうり","品目コード":"06","調査期間_西暦":"2024-09-16","価格":836.0,"reg1":636.0},{"品目名":"きゅうり","品目コード":"06","調査期間_西暦":"2024-09-23","価格":796.0,"reg1":636.212},{"品目名":"きゅうり","品目コード":"06","調査期間_西暦":"2024-09-30","価格":821.0,"reg1":636.423},{"品目名":"きゅうり","品目コード":"06","調査期間_西暦":"2024-10-07","価格":null,"reg1":null},{"品目名":"きゅうり","品目コード":"06","調査期間_西暦":"2024-10-14","価格":null,"reg1":null},{"品目名":"きゅうり","品目コード":"06","調査期間_西暦":"2024-10-21","価格":null,"reg1":null},{"品目名":"きゅうり","品目コード":"06","調査期間_西暦":"2024-10-28","価格":null,"reg1":null},{"品目名":"きゅうり","品目コード":"06","調査期間_西暦":"2024-11-04","価格":null,"reg1":null},{"品目名":"きゅうり","品目コード":"06","調査期間_西暦":"2024-11-11","価格":null,"reg1":null},{"品目名":"きゅうり","品目コード":"06","調査期間_西暦":"2024-11-18","価格":null,"reg1":null},{"品目名":"きゅうり","品目コード":"06","調査期間_西暦":"2024-11-25","価格":null,"reg1":null},{"品目名":"きゅうり","品目コード":"06","調査期間_西暦":"2024-12-02","価格":null,"reg1":null},{"品目名":"きゅうり","品目コード":"06","調査期間_西暦":"2024-12-09","価格":null,"reg1":null},{"品目名":"きゅうり","品目コード":"06","調査期間_西暦":"2024-12-16","価格":null,"reg1":null},{"品目名":"きゅうり","品目コード":"06","調査期間_西暦":"2024-12-23","価格":null,"reg1":null},{"品目名":"きゅうり","品目コード":"06","調査期間_西暦":"2025-01-06","価格":null,"reg1":null},{"品目名":"きゅうり","品目コード":"06","調査期間_西暦":"2025-01-13","価格":null,"reg1":null},{"品目名":"きゅうり","品目コード":"06","調査期間_西暦":"2025-01-20","価格":null,"reg1":null},{"品目名":"きゅうり","品目コード":"06","調査期間_西暦":"2025-01-27","価格":null,"reg1":null},{"品目名":"きゅうり","品目コード":"06","調査期間_西暦":"2025-02-03","価格":null,"reg1":null},{"品目名":"きゅうり","品目コード":"06","調査期間_西暦":"2025-02-10","価格":null,"reg1":null},{"品目名":"きゅうり","品目コード":"06","調査期間_西暦":"2025-02-17","価格":null,"reg1":null},{"品目名":"きゅうり","品目コード":"06","調査期間_西暦":"2025-02-24","価格":null,"reg1":null},{"品目名":"きゅうり","品目コード":"06","調査期間_西暦":"2025-03-03","価格":null,"reg1":null},{"品目名":"きゅうり","品目コード":"06","調査期間_西暦":"2025-03-10","価格":null,"reg1":null},{"品目名":"きゅうり","品目コード":"06","調査期間_西暦":"2025-03-17","価格":null,"reg1":null},{"品目名":"きゅうり","品目コード":"06","調査期間_西暦":"2025-03-24","価格":null,"reg1":null},{"品目名":"きゅうり","品目コード":"06","調査期間_西暦":"2025-04-01","価格":706.0,"reg1":641.709},{"品目名":"きゅうり","品目コード":"06","調査期間_西暦":"2025-04-07","価格":683.0,"reg1":641.921},{"品目名":"きゅうり","品目コード":"06","調査期間_西暦":"2025-04-14","価格":657.0,"reg1":642.132},{"品目名":"きゅうり","品目コード":"06","調査期間_西暦":"2025-04-21","価格":629.0,"reg1":642.343},{"品目名":"きゅうり","品目コード":"06","調査期間_西暦":"2025-04-28","価格":617.0,"reg1":642.555},{"品目名":"きゅうり","品目コード":"06","調査期間_西暦":"2025-05-12","価格":586.0,"reg1":642.766},{"品目名":"きゅうり","品目コード":"06","調査期間_西暦":"2025-05-19","価格":581.0,"reg1":642.978},{"品目名":"きゅうり","品目コード":"06","調査期間_西暦":"2025-05-26","価格":564.0,"reg1":643.189},{"品目名":"きゅうり","品目コード":"06","調査期間_西暦":"2025-06-02","価格":595.0,"reg1":643.401},{"品目名":"きゅうり","品目コード":"06","調査期間_西暦":"2025-06-09","価格":612.0,"reg1":643.612},{"品目名":"きゅうり","品目コード":"06","調査期間_西暦":"2025-06-16","価格":615.0,"reg1":643.823},{"品目名":"きゅうり","品目コード":"06","調査期間_西暦":"2025-06-23","価格":623.0,"reg1":644.035},{"品目名":"きゅうり","品目コード":"06","調査期間_西暦":"2025-06-30","価格":621.0,"reg1":644.246},{"品目名":"きゅうり","品目コード":"06","調査期間_西暦":"2025-07-07","価格":646.0,"reg1":644.458},{"品目名":"きゅうり","品目コード":"06","調査期間_西暦":"2025-07-14","価格":637.0,"reg1":644.669},{"品目名":"きゅうり","品目コード":"06","調査期間_西暦":"2025-07-21","価格":636.0,"reg1":644.881},{"品目名":"きゅうり","品目コード":"06","調査期間_西暦":"2025-07-28","価格":640.0,"reg1":645.092},{"品目名":"きゅうり","品目コード":"06","調査期間_西暦":"2025-08-04","価格":646.0,"reg1":645.304},{"品目名":"きゅうり","品目コード":"06","調査期間_西暦":"2025-08-18","価格":754.0,"reg1":645.515},{"品目名":"きゅうり","品目コード":"06","調査期間_西暦":"2025-08-25","価格":778.0,"reg1":645.726},{"品目名":"きゅうり","品目コード":"06","調査期間_西暦":"2025-09-01","価格":792.0,"reg1":645.938},{"品目名":"きゅうり","品目コード":"06","調査期間_西暦":"2025-09-08","価格":775.0,"reg1":646.149},{"品目名":"きゅうり","品目コード":"06","調査期間_西暦":"2025-09-15","価格":771.0,"reg1":646.361},{"品目名":"きゅうり","品目コード":"06","調査期間_西暦":"2025-09-22","価格":788.0,"reg1":646.572},{"品目名":"きゅうり","品目コード":"06","調査期間_西暦":"2025-09-29","価格":827.0,"reg1":646.784},{"品目名":"きゅうり","品目コード":"06","調査期間_西暦":"2025-10-06","価格":null,"reg1":null},{"品目名":"きゅうり","品目コード":"06","調査期間_西暦":"2025-10-13","価格":null,"reg1":null},{"品目名":"きゅうり","品目コード":"06","調査期間_西暦":"2025-10-20","価格":null,"reg1":null},{"品目名":"きゅうり","品目コード":"06","調査期間_西暦":"2025-10-27","価格":null,"reg1":null},{"品目名":"きゅうり","品目コード":"06","調査期間_西暦":"2025-11-10","価格":null,"reg1":null},{"品目名":"きゅうり","品目コード":"06","調査期間_西暦":"2025-11-17","価格":null,"reg1":null},{"品目名":"きゅうり","品目コード":"06","調査期間_西暦":"2025-11-24","価格":null,"reg1":null},{"品目名":"きゅうり","品目コード":"06","調査期間_西暦":"2025-12-01","価格":null,"reg1":null},{"品目名":"きゅうり","品目コード":"06","調査期間_西暦":"2025-12-08","価格":null,"reg1":null},{"品目名":"きゅうり","品目コード":"06","調査期間_西暦":"2025-12-15","価格":null,"reg1":null},{"品目名":"きゅうり","品目コード":"06","調査期間_西暦":"2025-12-22","価格":null,"reg1":null},{"品目名":"きゅうり","品目コード":"06","調査期間_西暦":"2026-01-05","価格":null,"reg1":null},{"品目名":"きゅうり","品目コード":"06","調査期間_西暦":"2026-01-26","価格":null,"reg1":null},{"品目名":"きゅうり","品目コード":"06","調査期間_西暦":"2026-02-02","価格":null,"reg1":null},{"品目名":"きゅうり","品目コード":"06","調査期間_西暦":"2026-02-09","価格":null,"reg1":null},{"品目名":"きゅうり","品目コード":"06","調査期間_西暦":"2026-02-16","価格":null,"reg1":null},{"品目名":"きゅうり","品目コード":"06","調査期間_西暦":"2026-02-23","価格":null,"reg1":null},{"品目名":"きゅうり","品目コード":"06","調査期間_西暦":"2026-03-02","価格":null,"reg1":null},{"品目名":"きゅうり","品目コード":"06","調査期間_西暦":"2026-03-09","価格":null,"reg1":null},{"品目名":"きゅうり","品目コード":"06","調査期間_西暦":"2026-03-16","価格":null,"reg1":null},{"品目名":"きゅうり","品目コード":"06","調査期間_西暦":"2026-03-23","価格":null,"reg1":null},{"品目名":"きゅうり","品目コード":"06","調査期間_西暦":"2026-04-06","価格":668.0,"reg1":651.435},{"品目名":"きゅうり","品目コード":"06","調査期間_西暦":"2026-04-13","価格":651.0,"reg1":651.647},{"品目名":"きゅうり","品目コード":"06","調査期間_西暦":"2026-04-20","価格":649.0,"reg1":651.858},{"品目名":"きゅうり","品目コード":"06","調査期間_西暦":"2026-04-27","価格":644.0,"reg1":652.07},{"品目名":"きゅうり","品目コード":"06","調査期間_西暦":"2026-05-11","価格":652.0,"reg1":652.281},{"品目名":"きゅうり","品目コード":"06","調査期間_西暦":"2026-05-18","価格":634.0,"reg1":652.492},{"品目名":"きゅうり","品目コード":"06","調査期間_西暦":"2026-05-25","価格":604.0,"reg1":652.704},{"品目名":"きゅうり","品目コード":"06","調査期間_西暦":"2026-06-01","価格":593.0,"reg1":652.915},{"品目名":"きゅうり","品目コード":"06","調査期間_西暦":"2026-06-08","価格":603.0,"reg1":653.127}]